<?xml version="1.0" encoding="UTF-8"?>
<list>
	<item id="2600" type="Weapon" name="襲擊劍*卡里埔士劍">
		<set name="icon" val="icon.weapon_dual_sword_i00" />
		<set name="default_action" val="equip" />
		<set name="weapon_type" val="dual" />
		<set name="bodypart" val="lrhand" />
		<set name="random_damage" val="10" />
		<set name="attack_range" val="40" />
		<set name="damage_range" val="0;0;44;120" />
		<set name="immediate_effect" val="1" />
		<set name="crystal_count" val="803" />
		<set name="crystal_type" val="b" />
		<set name="material" val="fine_steel" />
		<set name="weight" val="2190" />
		<set name="price" val="6022600" />
		<set name="soulshots" val="1" />
		<set name="spiritshots" val="1" />
		<set name="enchant_enabled" val="1" />
		<set name="enchant4_skill" val="3046-10" />
		<for>
			<set order="0x08" stat="pAtk" val="204" />
			<set order="0x08" stat="mAtk" val="89" />
			<set order="0x08" stat="rCrit" val="8" />
			<set order="0x08" stat="pAtkSpd" val="325" />
			<enchant val="0" order="0x0C" stat="pAtk" />
			<enchant val="0" order="0x0C" stat="mAtk" />
		</for>
	</item>
	<item id="2601" type="Weapon" name="襲擊劍*極限之劍">
		<set name="icon" val="icon.weapon_dual_sword_i00" />
		<set name="default_action" val="equip" />
		<set name="weapon_type" val="dual" />
		<set name="bodypart" val="lrhand" />
		<set name="random_damage" val="10" />
		<set name="attack_range" val="40" />
		<set name="damage_range" val="0;0;44;120" />
		<set name="immediate_effect" val="1" />
		<set name="crystal_count" val="803" />
		<set name="crystal_type" val="b" />
		<set name="material" val="fine_steel" />
		<set name="weight" val="2170" />
		<set name="price" val="6022600" />
		<set name="soulshots" val="1" />
		<set name="spiritshots" val="1" />
		<set name="enchant_enabled" val="1" />
		<set name="enchant4_skill" val="3042-10" />
		<for>
			<set order="0x08" stat="pAtk" val="204" />
			<set order="0x08" stat="mAtk" val="89" />
			<set order="0x08" stat="rCrit" val="8" />
			<set order="0x08" stat="pAtkSpd" val="325" />
			<enchant val="0" order="0x0C" stat="pAtk" />
			<enchant val="0" order="0x0C" stat="mAtk" />
		</for>
	</item>
	<item id="2602" type="Weapon" name="襲擊劍*迷惑之劍">
		<set name="icon" val="icon.weapon_dual_sword_i00" />
		<set name="default_action" val="equip" />
		<set name="weapon_type" val="dual" />
		<set name="bodypart" val="lrhand" />
		<set name="random_damage" val="10" />
		<set name="attack_range" val="40" />
		<set name="damage_range" val="0;0;44;120" />
		<set name="immediate_effect" val="1" />
		<set name="crystal_count" val="803" />
		<set name="crystal_type" val="b" />
		<set name="material" val="fine_steel" />
		<set name="weight" val="2180" />
		<set name="price" val="6022600" />
		<set name="soulshots" val="1" />
		<set name="spiritshots" val="1" />
		<set name="enchant_enabled" val="1" />
		<set name="enchant4_skill" val="3013-1" />
		<for>
			<set order="0x08" stat="pAtk" val="204" />
			<set order="0x08" stat="mAtk" val="89" />
			<set order="0x08" stat="rCrit" val="8" />
			<set order="0x08" stat="pAtkSpd" val="325" />
			<enchant val="0" order="0x0C" stat="pAtk" />
			<enchant val="0" order="0x0C" stat="mAtk" />
		</for>
	</item>
	<item id="2603" type="Weapon" name="襲擊劍*夢魘劍">
		<set name="icon" val="icon.weapon_dual_sword_i00" />
		<set name="default_action" val="equip" />
		<set name="weapon_type" val="dual" />
		<set name="bodypart" val="lrhand" />
		<set name="random_damage" val="10" />
		<set name="attack_range" val="40" />
		<set name="damage_range" val="0;0;44;120" />
		<set name="immediate_effect" val="1" />
		<set name="crystal_count" val="803" />
		<set name="crystal_type" val="b" />
		<set name="material" val="fine_steel" />
		<set name="weight" val="2170" />
		<set name="price" val="6022600" />
		<set name="soulshots" val="1" />
		<set name="spiritshots" val="1" />
		<set name="enchant_enabled" val="1" />
		<set name="enchant4_skill" val="3044-10" />
		<for>
			<set order="0x08" stat="pAtk" val="204" />
			<set order="0x08" stat="mAtk" val="89" />
			<set order="0x08" stat="rCrit" val="8" />
			<set order="0x08" stat="pAtkSpd" val="325" />
			<enchant val="0" order="0x0C" stat="pAtk" />
			<enchant val="0" order="0x0C" stat="mAtk" />
		</for>
	</item>
	<item id="2604" type="Weapon" name="襲擊劍*大和劍">
		<set name="icon" val="icon.weapon_dual_sword_i00" />
		<set name="default_action" val="equip" />
		<set name="weapon_type" val="dual" />
		<set name="bodypart" val="lrhand" />
		<set name="random_damage" val="10" />
		<set name="attack_range" val="40" />
		<set name="damage_range" val="0;0;44;120" />
		<set name="immediate_effect" val="1" />
		<set name="crystal_count" val="803" />
		<set name="crystal_type" val="b" />
		<set name="material" val="fine_steel" />
		<set name="weight" val="2170" />
		<set name="price" val="6022600" />
		<set name="soulshots" val="1" />
		<set name="spiritshots" val="1" />
		<set name="enchant_enabled" val="1" />
		<set name="enchant4_skill" val="3045-10" />
		<for>
			<set order="0x08" stat="pAtk" val="204" />
			<set order="0x08" stat="mAtk" val="89" />
			<set order="0x08" stat="rCrit" val="8" />
			<set order="0x08" stat="pAtkSpd" val="325" />
			<enchant val="0" order="0x0C" stat="pAtk" />
			<enchant val="0" order="0x0C" stat="mAtk" />
		</for>
	</item>
	<item id="2605" type="Weapon" name="襲擊劍*瑟魯基長劍">
		<set name="icon" val="icon.weapon_dual_sword_i00" />
		<set name="default_action" val="equip" />
		<set name="weapon_type" val="dual" />
		<set name="bodypart" val="lrhand" />
		<set name="random_damage" val="10" />
		<set name="attack_range" val="40" />
		<set name="damage_range" val="0;0;44;120" />
		<set name="immediate_effect" val="1" />
		<set name="crystal_count" val="979" />
		<set name="crystal_type" val="b" />
		<set name="material" val="fine_steel" />
		<set name="weight" val="2130" />
		<set name="price" val="7344400" />
		<set name="soulshots" val="1" />
		<set name="spiritshots" val="1" />
		<set name="enchant_enabled" val="1" />
		<set name="enchant4_skill" val="3044-12" />
		<for>
			<set order="0x08" stat="pAtk" val="220" />
			<set order="0x08" stat="mAtk" val="94" />
			<set order="0x08" stat="rCrit" val="8" />
			<set order="0x08" stat="pAtkSpd" val="325" />
			<enchant val="0" order="0x0C" stat="pAtk" />
			<enchant val="0" order="0x0C" stat="mAtk" />
		</for>
	</item>
	<item id="2606" type="Weapon" name="卡里埔士劍*卡里埔士劍">
		<set name="icon" val="icon.weapon_dual_sword_i00" />
		<set name="default_action" val="equip" />
		<set name="weapon_type" val="dual" />
		<set name="bodypart" val="lrhand" />
		<set name="random_damage" val="10" />
		<set name="attack_range" val="40" />
		<set name="damage_range" val="0;0;44;120" />
		<set name="immediate_effect" val="1" />
		<set name="crystal_count" val="891" />
		<set name="crystal_type" val="b" />
		<set name="material" val="fine_steel" />
		<set name="weight" val="2140" />
		<set name="price" val="6680500" />
		<set name="soulshots" val="1" />
		<set name="spiritshots" val="1" />
		<set name="enchant_enabled" val="1" />
		<set name="enchant4_skill" val="3042-11" />
		<for>
			<set order="0x08" stat="pAtk" val="213" />
			<set order="0x08" stat="mAtk" val="91" />
			<set order="0x08" stat="rCrit" val="8" />
			<set order="0x08" stat="pAtkSpd" val="325" />
			<enchant val="0" order="0x0C" stat="pAtk" />
			<enchant val="0" order="0x0C" stat="mAtk" />
		</for>
	</item>
	<item id="2607" type="Weapon" name="卡里埔士劍*極限之劍">
		<set name="icon" val="icon.weapon_dual_sword_i00" />
		<set name="default_action" val="equip" />
		<set name="weapon_type" val="dual" />
		<set name="bodypart" val="lrhand" />
		<set name="random_damage" val="10" />
		<set name="attack_range" val="40" />
		<set name="damage_range" val="0;0;44;120" />
		<set name="immediate_effect" val="1" />
		<set name="crystal_count" val="891" />
		<set name="crystal_type" val="b" />
		<set name="material" val="fine_steel" />
		<set name="weight" val="2150" />
		<set name="price" val="6680500" />
		<set name="soulshots" val="1" />
		<set name="spiritshots" val="1" />
		<set name="enchant_enabled" val="1" />
		<set name="enchant4_skill" val="3013-1" />
		<for>
			<set order="0x08" stat="pAtk" val="213" />
			<set order="0x08" stat="mAtk" val="91" />
			<set order="0x08" stat="rCrit" val="8" />
			<set order="0x08" stat="pAtkSpd" val="325" />
			<enchant val="0" order="0x0C" stat="pAtk" />
			<enchant val="0" order="0x0C" stat="mAtk" />
		</for>
	</item>
	<item id="2608" type="Weapon" name="卡里埔士劍*迷惑之劍">
		<set name="icon" val="icon.weapon_dual_sword_i00" />
		<set name="default_action" val="equip" />
		<set name="weapon_type" val="dual" />
		<set name="bodypart" val="lrhand" />
		<set name="random_damage" val="10" />
		<set name="attack_range" val="40" />
		<set name="damage_range" val="0;0;44;120" />
		<set name="immediate_effect" val="1" />
		<set name="crystal_count" val="891" />
		<set name="crystal_type" val="b" />
		<set name="material" val="fine_steel" />
		<set name="weight" val="2140" />
		<set name="price" val="6680500" />
		<set name="soulshots" val="1" />
		<set name="spiritshots" val="1" />
		<set name="enchant_enabled" val="1" />
		<set name="enchant4_skill" val="3044-11" />
		<for>
			<set order="0x08" stat="pAtk" val="213" />
			<set order="0x08" stat="mAtk" val="91" />
			<set order="0x08" stat="rCrit" val="8" />
			<set order="0x08" stat="pAtkSpd" val="325" />
			<enchant val="0" order="0x0C" stat="pAtk" />
			<enchant val="0" order="0x0C" stat="mAtk" />
		</for>
	</item>
	<item id="2609" type="Weapon" name="卡里埔士劍*夢魘劍">
		<set name="icon" val="icon.weapon_dual_sword_i00" />
		<set name="default_action" val="equip" />
		<set name="weapon_type" val="dual" />
		<set name="bodypart" val="lrhand" />
		<set name="random_damage" val="10" />
		<set name="attack_range" val="40" />
		<set name="damage_range" val="0;0;44;120" />
		<set name="immediate_effect" val="1" />
		<set name="crystal_count" val="891" />
		<set name="crystal_type" val="b" />
		<set name="material" val="fine_steel" />
		<set name="weight" val="2170" />
		<set name="price" val="6680500" />
		<set name="soulshots" val="1" />
		<set name="spiritshots" val="1" />
		<set name="enchant_enabled" val="1" />
		<set name="enchant4_skill" val="3045-11" />
		<for>
			<set order="0x08" stat="pAtk" val="213" />
			<set order="0x08" stat="mAtk" val="91" />
			<set order="0x08" stat="rCrit" val="8" />
			<set order="0x08" stat="pAtkSpd" val="325" />
			<enchant val="0" order="0x0C" stat="pAtk" />
			<enchant val="0" order="0x0C" stat="mAtk" />
		</for>
	</item>
	<item id="2610" type="Weapon" name="卡里埔士劍*大和劍">
		<set name="icon" val="icon.weapon_dual_sword_i00" />
		<set name="default_action" val="equip" />
		<set name="weapon_type" val="dual" />
		<set name="bodypart" val="lrhand" />
		<set name="random_damage" val="10" />
		<set name="attack_range" val="40" />
		<set name="damage_range" val="0;0;44;120" />
		<set name="immediate_effect" val="1" />
		<set name="crystal_count" val="891" />
		<set name="crystal_type" val="b" />
		<set name="material" val="fine_steel" />
		<set name="weight" val="2150" />
		<set name="price" val="6680500" />
		<set name="soulshots" val="1" />
		<set name="spiritshots" val="1" />
		<set name="enchant_enabled" val="1" />
		<set name="enchant4_skill" val="3046-11" />
		<for>
			<set order="0x08" stat="pAtk" val="213" />
			<set order="0x08" stat="mAtk" val="91" />
			<set order="0x08" stat="rCrit" val="8" />
			<set order="0x08" stat="pAtkSpd" val="325" />
			<enchant val="0" order="0x0C" stat="pAtk" />
			<enchant val="0" order="0x0C" stat="mAtk" />
		</for>
	</item>
	<item id="2611" type="Weapon" name="卡里埔士劍*瑟魯基長劍">
		<set name="icon" val="icon.weapon_dual_sword_i00" />
		<set name="default_action" val="equip" />
		<set name="weapon_type" val="dual" />
		<set name="bodypart" val="lrhand" />
		<set name="random_damage" val="10" />
		<set name="attack_range" val="40" />
		<set name="damage_range" val="0;0;44;120" />
		<set name="immediate_effect" val="1" />
		<set name="crystal_count" val="1164" />
		<set name="crystal_type" val="b" />
		<set name="material" val="fine_steel" />
		<set name="weight" val="2120" />
		<set name="price" val="8729600" />
		<set name="soulshots" val="1" />
		<set name="spiritshots" val="1" />
		<set name="enchant_enabled" val="1" />
		<set name="enchant4_skill" val="3045-13" />
		<for>
			<set order="0x08" stat="pAtk" val="228" />
			<set order="0x08" stat="mAtk" val="97" />
			<set order="0x08" stat="rCrit" val="8" />
			<set order="0x08" stat="pAtkSpd" val="325" />
			<enchant val="0" order="0x0C" stat="pAtk" />
			<enchant val="0" order="0x0C" stat="mAtk" />
		</for>
	</item>
	<item id="2612" type="Weapon" name="極限之劍*極限之劍">
		<set name="icon" val="icon.weapon_dual_sword_i00" />
		<set name="default_action" val="equip" />
		<set name="weapon_type" val="dual" />
		<set name="bodypart" val="lrhand" />
		<set name="random_damage" val="10" />
		<set name="attack_range" val="40" />
		<set name="damage_range" val="0;0;44;120" />
		<set name="immediate_effect" val="1" />
		<set name="crystal_count" val="891" />
		<set name="crystal_type" val="b" />
		<set name="material" val="fine_steel" />
		<set name="weight" val="2140" />
		<set name="price" val="6680500" />
		<set name="soulshots" val="1" />
		<set name="spiritshots" val="1" />
		<set name="enchant_enabled" val="1" />
		<set name="enchant4_skill" val="3042-11" />
		<for>
			<set order="0x08" stat="pAtk" val="213" />
			<set order="0x08" stat="mAtk" val="91" />
			<set order="0x08" stat="rCrit" val="8" />
			<set order="0x08" stat="pAtkSpd" val="325" />
			<enchant val="0" order="0x0C" stat="pAtk" />
			<enchant val="0" order="0x0C" stat="mAtk" />
		</for>
	</item>
	<item id="2613" type="Weapon" name="極限之劍*迷惑之劍">
		<set name="icon" val="icon.weapon_dual_sword_i00" />
		<set name="default_action" val="equip" />
		<set name="weapon_type" val="dual" />
		<set name="bodypart" val="lrhand" />
		<set name="random_damage" val="10" />
		<set name="attack_range" val="40" />
		<set name="damage_range" val="0;0;44;120" />
		<set name="immediate_effect" val="1" />
		<set name="crystal_count" val="891" />
		<set name="crystal_type" val="b" />
		<set name="material" val="fine_steel" />
		<set name="weight" val="2140" />
		<set name="price" val="6680500" />
		<set name="soulshots" val="1" />
		<set name="spiritshots" val="1" />
		<set name="enchant_enabled" val="1" />
		<set name="enchant4_skill" val="3013-1" />
		<for>
			<set order="0x08" stat="pAtk" val="213" />
			<set order="0x08" stat="mAtk" val="91" />
			<set order="0x08" stat="rCrit" val="8" />
			<set order="0x08" stat="pAtkSpd" val="325" />
			<enchant val="0" order="0x0C" stat="pAtk" />
			<enchant val="0" order="0x0C" stat="mAtk" />
		</for>
	</item>
	<item id="2614" type="Weapon" name="極限之劍*夢魘劍">
		<set name="icon" val="icon.weapon_dual_sword_i00" />
		<set name="default_action" val="equip" />
		<set name="weapon_type" val="dual" />
		<set name="bodypart" val="lrhand" />
		<set name="random_damage" val="10" />
		<set name="attack_range" val="40" />
		<set name="damage_range" val="0;0;44;120" />
		<set name="immediate_effect" val="1" />
		<set name="crystal_count" val="891" />
		<set name="crystal_type" val="b" />
		<set name="material" val="fine_steel" />
		<set name="weight" val="2130" />
		<set name="price" val="6680500" />
		<set name="soulshots" val="1" />
		<set name="spiritshots" val="1" />
		<set name="enchant_enabled" val="1" />
		<set name="enchant4_skill" val="3044-11" />
		<for>
			<set order="0x08" stat="pAtk" val="213" />
			<set order="0x08" stat="mAtk" val="91" />
			<set order="0x08" stat="rCrit" val="8" />
			<set order="0x08" stat="pAtkSpd" val="325" />
			<enchant val="0" order="0x0C" stat="pAtk" />
			<enchant val="0" order="0x0C" stat="mAtk" />
		</for>
	</item>
	<item id="2615" type="Weapon" name="極限之劍*大和劍">
		<set name="icon" val="icon.weapon_dual_sword_i00" />
		<set name="default_action" val="equip" />
		<set name="weapon_type" val="dual" />
		<set name="bodypart" val="lrhand" />
		<set name="random_damage" val="10" />
		<set name="attack_range" val="40" />
		<set name="damage_range" val="0;0;44;120" />
		<set name="immediate_effect" val="1" />
		<set name="crystal_count" val="891" />
		<set name="crystal_type" val="b" />
		<set name="material" val="fine_steel" />
		<set name="weight" val="2120" />
		<set name="price" val="6680500" />
		<set name="soulshots" val="1" />
		<set name="spiritshots" val="1" />
		<set name="enchant_enabled" val="1" />
		<set name="enchant4_skill" val="3045-11" />
		<for>
			<set order="0x08" stat="pAtk" val="213" />
			<set order="0x08" stat="mAtk" val="91" />
			<set order="0x08" stat="rCrit" val="8" />
			<set order="0x08" stat="pAtkSpd" val="325" />
			<enchant val="0" order="0x0C" stat="pAtk" />
			<enchant val="0" order="0x0C" stat="mAtk" />
		</for>
	</item>
	<item id="2616" type="Weapon" name="極限之劍*瑟魯基長劍">
		<set name="icon" val="icon.weapon_dual_sword_i00" />
		<set name="default_action" val="equip" />
		<set name="weapon_type" val="dual" />
		<set name="bodypart" val="lrhand" />
		<set name="random_damage" val="10" />
		<set name="attack_range" val="40" />
		<set name="damage_range" val="0;0;44;120" />
		<set name="immediate_effect" val="1" />
		<set name="crystal_count" val="1164" />
		<set name="crystal_type" val="b" />
		<set name="material" val="fine_steel" />
		<set name="weight" val="2100" />
		<set name="price" val="8729600" />
		<set name="soulshots" val="1" />
		<set name="spiritshots" val="1" />
		<set name="enchant_enabled" val="1" />
		<set name="enchant4_skill" val="3046-13" />
		<for>
			<set order="0x08" stat="pAtk" val="228" />
			<set order="0x08" stat="mAtk" val="97" />
			<set order="0x08" stat="rCrit" val="8" />
			<set order="0x08" stat="pAtkSpd" val="325" />
			<enchant val="0" order="0x0C" stat="pAtk" />
			<enchant val="0" order="0x0C" stat="mAtk" />
		</for>
	</item>
	<item id="2617" type="Weapon" name="迷惑之劍*迷惑之劍">
		<set name="icon" val="icon.weapon_dual_sword_i00" />
		<set name="default_action" val="equip" />
		<set name="weapon_type" val="dual" />
		<set name="bodypart" val="lrhand" />
		<set name="random_damage" val="10" />
		<set name="attack_range" val="40" />
		<set name="damage_range" val="0;0;44;120" />
		<set name="immediate_effect" val="1" />
		<set name="crystal_count" val="891" />
		<set name="crystal_type" val="b" />
		<set name="material" val="fine_steel" />
		<set name="weight" val="2150" />
		<set name="price" val="6680500" />
		<set name="soulshots" val="1" />
		<set name="spiritshots" val="1" />
		<set name="enchant_enabled" val="1" />
		<set name="enchant4_skill" val="3046-11" />
		<for>
			<set order="0x08" stat="pAtk" val="213" />
			<set order="0x08" stat="mAtk" val="91" />
			<set order="0x08" stat="rCrit" val="8" />
			<set order="0x08" stat="pAtkSpd" val="325" />
			<enchant val="0" order="0x0C" stat="pAtk" />
			<enchant val="0" order="0x0C" stat="mAtk" />
		</for>
	</item>
	<item id="2618" type="Weapon" name="迷惑之劍*夢魘劍">
		<set name="icon" val="icon.weapon_dual_sword_i00" />
		<set name="default_action" val="equip" />
		<set name="weapon_type" val="dual" />
		<set name="bodypart" val="lrhand" />
		<set name="random_damage" val="10" />
		<set name="attack_range" val="40" />
		<set name="damage_range" val="0;0;44;120" />
		<set name="immediate_effect" val="1" />
		<set name="crystal_count" val="891" />
		<set name="crystal_type" val="b" />
		<set name="material" val="fine_steel" />
		<set name="weight" val="2130" />
		<set name="price" val="6680500" />
		<set name="soulshots" val="1" />
		<set name="spiritshots" val="1" />
		<set name="enchant_enabled" val="1" />
		<set name="enchant4_skill" val="3042-11" />
		<for>
			<set order="0x08" stat="pAtk" val="213" />
			<set order="0x08" stat="mAtk" val="91" />
			<set order="0x08" stat="rCrit" val="8" />
			<set order="0x08" stat="pAtkSpd" val="325" />
			<enchant val="0" order="0x0C" stat="pAtk" />
			<enchant val="0" order="0x0C" stat="mAtk" />
		</for>
	</item>
	<item id="2619" type="Weapon" name="迷惑之劍*大和劍">
		<set name="icon" val="icon.weapon_dual_sword_i00" />
		<set name="default_action" val="equip" />
		<set name="weapon_type" val="dual" />
		<set name="bodypart" val="lrhand" />
		<set name="random_damage" val="10" />
		<set name="attack_range" val="40" />
		<set name="damage_range" val="0;0;44;120" />
		<set name="immediate_effect" val="1" />
		<set name="crystal_count" val="891" />
		<set name="crystal_type" val="b" />
		<set name="material" val="fine_steel" />
		<set name="weight" val="2140" />
		<set name="price" val="6680500" />
		<set name="soulshots" val="1" />
		<set name="spiritshots" val="1" />
		<set name="enchant_enabled" val="1" />
		<set name="enchant4_skill" val="3013-1" />
		<for>
			<set order="0x08" stat="pAtk" val="213" />
			<set order="0x08" stat="mAtk" val="91" />
			<set order="0x08" stat="rCrit" val="8" />
			<set order="0x08" stat="pAtkSpd" val="325" />
			<enchant val="0" order="0x0C" stat="pAtk" />
			<enchant val="0" order="0x0C" stat="mAtk" />
		</for>
	</item>
	<item id="2620" type="Weapon" name="迷惑之劍*瑟魯基長劍">
		<set name="icon" val="icon.weapon_dual_sword_i00" />
		<set name="default_action" val="equip" />
		<set name="weapon_type" val="dual" />
		<set name="bodypart" val="lrhand" />
		<set name="random_damage" val="10" />
		<set name="attack_range" val="40" />
		<set name="damage_range" val="0;0;44;120" />
		<set name="immediate_effect" val="1" />
		<set name="crystal_count" val="1164" />
		<set name="crystal_type" val="b" />
		<set name="material" val="fine_steel" />
		<set name="weight" val="2110" />
		<set name="price" val="8729600" />
		<set name="soulshots" val="1" />
		<set name="spiritshots" val="1" />
		<set name="enchant_enabled" val="1" />
		<set name="enchant4_skill" val="3042-13" />
		<for>
			<set order="0x08" stat="pAtk" val="228" />
			<set order="0x08" stat="mAtk" val="97" />
			<set order="0x08" stat="rCrit" val="8" />
			<set order="0x08" stat="pAtkSpd" val="325" />
			<enchant val="0" order="0x0C" stat="pAtk" />
			<enchant val="0" order="0x0C" stat="mAtk" />
		</for>
	</item>
	<item id="2621" type="Weapon" name="夢魘劍*夢魘劍">
		<set name="icon" val="icon.weapon_dual_sword_i00" />
		<set name="default_action" val="equip" />
		<set name="weapon_type" val="dual" />
		<set name="bodypart" val="lrhand" />
		<set name="random_damage" val="10" />
		<set name="attack_range" val="40" />
		<set name="damage_range" val="0;0;44;120" />
		<set name="immediate_effect" val="1" />
		<set name="crystal_count" val="891" />
		<set name="crystal_type" val="b" />
		<set name="material" val="fine_steel" />
		<set name="weight" val="2130" />
		<set name="price" val="6680500" />
		<set name="soulshots" val="1" />
		<set name="spiritshots" val="1" />
		<set name="enchant_enabled" val="1" />
		<set name="enchant4_skill" val="3044-11" />
		<for>
			<set order="0x08" stat="pAtk" val="213" />
			<set order="0x08" stat="mAtk" val="91" />
			<set order="0x08" stat="rCrit" val="8" />
			<set order="0x08" stat="pAtkSpd" val="325" />
			<enchant val="0" order="0x0C" stat="pAtk" />
			<enchant val="0" order="0x0C" stat="mAtk" />
		</for>
	</item>
	<item id="2622" type="Weapon" name="夢魘劍*大和劍">
		<set name="icon" val="icon.weapon_dual_sword_i00" />
		<set name="default_action" val="equip" />
		<set name="weapon_type" val="dual" />
		<set name="bodypart" val="lrhand" />
		<set name="random_damage" val="10" />
		<set name="attack_range" val="40" />
		<set name="damage_range" val="0;0;44;120" />
		<set name="immediate_effect" val="1" />
		<set name="crystal_count" val="891" />
		<set name="crystal_type" val="b" />
		<set name="material" val="fine_steel" />
		<set name="weight" val="2140" />
		<set name="price" val="6680500" />
		<set name="soulshots" val="1" />
		<set name="spiritshots" val="1" />
		<set name="enchant_enabled" val="1" />
		<set name="enchant4_skill" val="3045-11" />
		<for>
			<set order="0x08" stat="pAtk" val="213" />
			<set order="0x08" stat="mAtk" val="91" />
			<set order="0x08" stat="rCrit" val="8" />
			<set order="0x08" stat="pAtkSpd" val="325" />
			<enchant val="0" order="0x0C" stat="pAtk" />
			<enchant val="0" order="0x0C" stat="mAtk" />
		</for>
	</item>
	<item id="2623" type="Weapon" name="夢魘劍*瑟魯基長劍">
		<set name="icon" val="icon.weapon_dual_sword_i00" />
		<set name="default_action" val="equip" />
		<set name="weapon_type" val="dual" />
		<set name="bodypart" val="lrhand" />
		<set name="random_damage" val="10" />
		<set name="attack_range" val="40" />
		<set name="damage_range" val="0;0;44;120" />
		<set name="immediate_effect" val="1" />
		<set name="crystal_count" val="1164" />
		<set name="crystal_type" val="b" />
		<set name="material" val="fine_steel" />
		<set name="weight" val="2080" />
		<set name="price" val="8729600" />
		<set name="soulshots" val="1" />
		<set name="spiritshots" val="1" />
		<set name="enchant_enabled" val="1" />
		<set name="enchant4_skill" val="3013-1" />
		<for>
			<set order="0x08" stat="pAtk" val="228" />
			<set order="0x08" stat="mAtk" val="97" />
			<set order="0x08" stat="rCrit" val="8" />
			<set order="0x08" stat="pAtkSpd" val="325" />
			<enchant val="0" order="0x0C" stat="pAtk" />
			<enchant val="0" order="0x0C" stat="mAtk" />
		</for>
	</item>
	<item id="2624" type="Weapon" name="大和劍*大和劍">
		<set name="icon" val="icon.weapon_dual_sword_i00" />
		<set name="default_action" val="equip" />
		<set name="weapon_type" val="dual" />
		<set name="bodypart" val="lrhand" />
		<set name="random_damage" val="10" />
		<set name="attack_range" val="40" />
		<set name="damage_range" val="0;0;44;120" />
		<set name="immediate_effect" val="1" />
		<set name="crystal_count" val="891" />
		<set name="crystal_type" val="b" />
		<set name="material" val="fine_steel" />
		<set name="weight" val="2120" />
		<set name="price" val="6680500" />
		<set name="soulshots" val="1" />
		<set name="spiritshots" val="1" />
		<set name="enchant_enabled" val="1" />
		<set name="enchant4_skill" val="3044-11" />
		<for>
			<set order="0x08" stat="pAtk" val="213" />
			<set order="0x08" stat="mAtk" val="91" />
			<set order="0x08" stat="rCrit" val="8" />
			<set order="0x08" stat="pAtkSpd" val="325" />
			<enchant val="0" order="0x0C" stat="pAtk" />
			<enchant val="0" order="0x0C" stat="mAtk" />
		</for>
	</item>
	<item id="2625" type="Weapon" name="大和劍*瑟魯基長劍">
		<set name="icon" val="icon.weapon_dual_sword_i00" />
		<set name="default_action" val="equip" />
		<set name="weapon_type" val="dual" />
		<set name="bodypart" val="lrhand" />
		<set name="random_damage" val="10" />
		<set name="attack_range" val="40" />
		<set name="damage_range" val="0;0;44;120" />
		<set name="immediate_effect" val="1" />
		<set name="crystal_count" val="1164" />
		<set name="crystal_type" val="b" />
		<set name="material" val="fine_steel" />
		<set name="weight" val="2090" />
		<set name="price" val="8729600" />
		<set name="soulshots" val="1" />
		<set name="spiritshots" val="1" />
		<set name="enchant_enabled" val="1" />
		<set name="enchant4_skill" val="3044-13" />
		<for>
			<set order="0x08" stat="pAtk" val="228" />
			<set order="0x08" stat="mAtk" val="97" />
			<set order="0x08" stat="rCrit" val="8" />
			<set order="0x08" stat="pAtkSpd" val="325" />
			<enchant val="0" order="0x0C" stat="pAtk" />
			<enchant val="0" order="0x0C" stat="mAtk" />
		</for>
	</item>
	<item id="2626" type="Weapon" name="瑟魯基長劍*瑟魯基長劍">
		<set name="icon" val="icon.weapon_dual_sword_i00" />
		<set name="default_action" val="equip" />
		<set name="weapon_type" val="dual" />
		<set name="bodypart" val="lrhand" />
		<set name="random_damage" val="10" />
		<set name="attack_range" val="40" />
		<set name="damage_range" val="0;0;44;120" />
		<set name="immediate_effect" val="1" />
		<set name="crystal_count" val="1346" />
		<set name="crystal_type" val="b" />
		<set name="material" val="fine_steel" />
		<set name="weight" val="2080" />
		<set name="price" val="10091400" />
		<set name="soulshots" val="1" />
		<set name="spiritshots" val="1" />
		<set name="enchant_enabled" val="1" />
		<set name="enchant4_skill" val="3045-14" />
		<for>
			<set order="0x08" stat="pAtk" val="236" />
			<set order="0x08" stat="mAtk" val="99" />
			<set order="0x08" stat="rCrit" val="8" />
			<set order="0x08" stat="pAtkSpd" val="325" />
			<enchant val="0" order="0x0C" stat="pAtk" />
			<enchant val="0" order="0x0C" stat="mAtk" />
		</for>
	</item>
	<item id="2627" type="EtcItem" name="挑戰者標章">
		<set name="icon" val="icon.etc_jewel_silver_i00" />
		<set name="immediate_effect" val="1" />
		<set name="material" val="steel" />
		<set name="is_tradable" val="false" />
		<set name="is_dropable" val="false" />
		<set name="is_sellable" val="false" />
		<set name="is_depositable" val="false" />
		<set name="is_stackable" val="true" />
		<set name="is_questitem" val="true" />
	</item>
	<item id="2628" type="EtcItem" name="凱許的信">
		<set name="icon" val="icon.etc_scroll_gray_i00" />
		<set name="immediate_effect" val="1" />
		<set name="material" val="steel" />
		<set name="is_tradable" val="false" />
		<set name="is_dropable" val="false" />
		<set name="is_sellable" val="false" />
		<set name="is_depositable" val="false" />
		<set name="is_stackable" val="true" />
		<set name="is_questitem" val="true" />
	</item>
	<item id="2629" type="EtcItem" name="觀察者之眼">
		<set name="icon" val="icon.etc_eyeball_i00" />
		<set name="immediate_effect" val="1" />
		<set name="material" val="steel" />
		<set name="is_tradable" val="false" />
		<set name="is_dropable" val="false" />
		<set name="is_sellable" val="false" />
		<set name="is_depositable" val="false" />
		<set name="is_stackable" val="true" />
		<set name="is_questitem" val="true" />
	</item>
	<item id="2630" type="EtcItem" name="觀察者之眼">
		<set name="icon" val="icon.etc_eyeball_i00" />
		<set name="immediate_effect" val="1" />
		<set name="material" val="steel" />
		<set name="is_tradable" val="false" />
		<set name="is_dropable" val="false" />
		<set name="is_sellable" val="false" />
		<set name="is_depositable" val="false" />
		<set name="is_stackable" val="true" />
		<set name="is_questitem" val="true" />
	</item>
	<item id="2631" type="EtcItem" name="西斯拉瑟的卷軸">
		<set name="icon" val="icon.etc_scroll_of_enchant_weapon_i01" />
		<set name="immediate_effect" val="1" />
		<set name="material" val="steel" />
		<set name="is_tradable" val="false" />
		<set name="is_dropable" val="false" />
		<set name="is_sellable" val="false" />
		<set name="is_depositable" val="false" />
		<set name="is_stackable" val="true" />
		<set name="is_questitem" val="true" />
	</item>
	<item id="2632" type="EtcItem" name="破碎鑰匙">
		<set name="icon" val="icon.etc_mold_i00" />
		<set name="immediate_effect" val="1" />
		<set name="material" val="steel" />
		<set name="is_tradable" val="false" />
		<set name="is_dropable" val="false" />
		<set name="is_sellable" val="false" />
		<set name="is_depositable" val="false" />
		<set name="is_stackable" val="true" />
		<set name="is_questitem" val="true" />
	</item>
	<item id="2633" type="EtcItem" name="使命標章">
		<set name="icon" val="icon.accessary_necklace_of_holy_spirit_i00" />
		<set name="immediate_effect" val="1" />
		<set name="material" val="steel" />
		<set name="is_tradable" val="false" />
		<set name="is_dropable" val="false" />
		<set name="is_sellable" val="false" />
		<set name="is_depositable" val="false" />
		<set name="is_stackable" val="true" />
		<set name="is_questitem" val="true" />
	</item>
	<item id="2634" type="EtcItem" name="德詩丁的信">
		<set name="icon" val="icon.etc_piece_of_paper_white_i00" />
		<set name="immediate_effect" val="1" />
		<set name="material" val="steel" />
		<set name="is_tradable" val="false" />
		<set name="is_dropable" val="false" />
		<set name="is_sellable" val="false" />
		<set name="is_depositable" val="false" />
		<set name="is_stackable" val="true" />
		<set name="is_questitem" val="true" />
	</item>
	<item id="2635" type="EtcItem" name="騎士之淚">
		<set name="icon" val="icon.etc_crystal_ball_red_i00" />
		<set name="immediate_effect" val="1" />
		<set name="material" val="steel" />
		<set name="is_tradable" val="false" />
		<set name="is_dropable" val="false" />
		<set name="is_sellable" val="false" />
		<set name="is_depositable" val="false" />
		<set name="is_stackable" val="true" />
		<set name="is_questitem" val="true" />
	</item>
	<item id="2636" type="EtcItem" name="奧比諾之鏡">
		<set name="icon" val="icon.etc_mirror_i00" />
		<set name="immediate_effect" val="1" />
		<set name="material" val="steel" />
		<set name="is_tradable" val="false" />
		<set name="is_dropable" val="false" />
		<set name="is_sellable" val="false" />
		<set name="is_depositable" val="false" />
		<set name="is_stackable" val="true" />
		<set name="is_questitem" val="true" />
	</item>
	<item id="2637" type="EtcItem" name="懺悔之淚">
		<set name="icon" val="icon.etc_crystal_ball_white_i00" />
		<set name="immediate_effect" val="1" />
		<set name="material" val="steel" />
		<set name="is_tradable" val="false" />
		<set name="is_dropable" val="false" />
		<set name="is_sellable" val="false" />
		<set name="is_depositable" val="false" />
		<set name="is_stackable" val="true" />
		<set name="is_questitem" val="true" />
	</item>
	<item id="2638" type="EtcItem" name="報告的片段">
		<set name="icon" val="icon.etc_leather_gray_i00" />
		<set name="immediate_effect" val="1" />
		<set name="material" val="steel" />
		<set name="is_tradable" val="false" />
		<set name="is_dropable" val="false" />
		<set name="is_sellable" val="false" />
		<set name="is_depositable" val="false" />
		<set name="is_stackable" val="true" />
		<set name="is_questitem" val="true" />
	</item>
	<item id="2639" type="EtcItem" name="塔利亞斯的報告">
		<set name="icon" val="icon.etc_letter_white_i00" />
		<set name="immediate_effect" val="1" />
		<set name="material" val="steel" />
		<set name="is_tradable" val="false" />
		<set name="is_dropable" val="false" />
		<set name="is_sellable" val="false" />
		<set name="is_depositable" val="false" />
		<set name="is_stackable" val="true" />
		<set name="is_questitem" val="true" />
	</item>
	<item id="2640" type="EtcItem" name="忠誠之淚">
		<set name="icon" val="icon.etc_crystal_ball_silver_i00" />
		<set name="immediate_effect" val="1" />
		<set name="material" val="steel" />
		<set name="is_tradable" val="false" />
		<set name="is_dropable" val="false" />
		<set name="is_sellable" val="false" />
		<set name="is_depositable" val="false" />
		<set name="is_stackable" val="true" />
		<set name="is_questitem" val="true" />
	</item>
	<item id="2641" type="EtcItem" name="義勇軍的遺物">
		<set name="icon" val="icon.etc_jewel_box_i00" />
		<set name="immediate_effect" val="1" />
		<set name="material" val="steel" />
		<set name="is_tradable" val="false" />
		<set name="is_dropable" val="false" />
		<set name="is_sellable" val="false" />
		<set name="is_depositable" val="false" />
		<set name="is_stackable" val="true" />
		<set name="is_questitem" val="true" />
	</item>
	<item id="2642" type="EtcItem" name="聖者的骨灰罈">
		<set name="icon" val="icon.etc_oil_pot_white_i00" />
		<set name="immediate_effect" val="1" />
		<set name="material" val="steel" />
		<set name="is_tradable" val="false" />
		<set name="is_dropable" val="false" />
		<set name="is_sellable" val="false" />
		<set name="is_depositable" val="false" />
		<set name="is_stackable" val="true" />
		<set name="is_questitem" val="true" />
	</item>
	<item id="2643" type="EtcItem" name="亞太法特的頭骨">
		<set name="icon" val="icon.etc_skull_white_i00" />
		<set name="immediate_effect" val="1" />
		<set name="material" val="steel" />
		<set name="is_tradable" val="false" />
		<set name="is_dropable" val="false" />
		<set name="is_sellable" val="false" />
		<set name="is_depositable" val="false" />
		<set name="is_stackable" val="true" />
		<set name="is_questitem" val="true" />
	</item>
	<item id="2644" type="EtcItem" name="亞太法特的肋骨">
		<set name="icon" val="icon.etc_rib_white_i00" />
		<set name="immediate_effect" val="1" />
		<set name="material" val="steel" />
		<set name="is_tradable" val="false" />
		<set name="is_dropable" val="false" />
		<set name="is_sellable" val="false" />
		<set name="is_depositable" val="false" />
		<set name="is_stackable" val="true" />
		<set name="is_questitem" val="true" />
	</item>
	<item id="2645" type="EtcItem" name="亞太法特的腿骨">
		<set name="icon" val="icon.etc_piece_bone_white_i00" />
		<set name="immediate_effect" val="1" />
		<set name="material" val="steel" />
		<set name="is_tradable" val="false" />
		<set name="is_dropable" val="false" />
		<set name="is_sellable" val="false" />
		<set name="is_depositable" val="false" />
		<set name="is_stackable" val="true" />
		<set name="is_questitem" val="true" />
	</item>
	<item id="2646" type="EtcItem" name="溫達伍德的信">
		<set name="icon" val="icon.etc_letter_blue_i00" />
		<set name="immediate_effect" val="1" />
		<set name="material" val="steel" />
		<set name="is_tradable" val="false" />
		<set name="is_dropable" val="false" />
		<set name="is_sellable" val="false" />
		<set name="is_depositable" val="false" />
		<set name="is_stackable" val="true" />
		<set name="is_questitem" val="true" />
	</item>
	<item id="2647" type="EtcItem" name="都普尼的信">
		<set name="icon" val="icon.etc_scroll_white_i00" />
		<set name="immediate_effect" val="1" />
		<set name="material" val="steel" />
		<set name="is_tradable" val="false" />
		<set name="is_dropable" val="false" />
		<set name="is_sellable" val="false" />
		<set name="is_depositable" val="false" />
		<set name="is_stackable" val="true" />
		<set name="is_questitem" val="true" />
	</item>
	<item id="2648" type="EtcItem" name="泰瑞的單子">
		<set name="icon" val="icon.etc_scroll_of_resurrection_i01" />
		<set name="immediate_effect" val="1" />
		<set name="material" val="steel" />
		<set name="is_tradable" val="false" />
		<set name="is_dropable" val="false" />
		<set name="is_sellable" val="false" />
		<set name="is_depositable" val="false" />
		<set name="is_stackable" val="true" />
		<set name="is_questitem" val="true" />
	</item>
	<item id="2649" type="EtcItem" name="泰瑞的單子">
		<set name="icon" val="icon.etc_scroll_of_return_i00" />
		<set name="immediate_effect" val="1" />
		<set name="material" val="steel" />
		<set name="is_tradable" val="false" />
		<set name="is_dropable" val="false" />
		<set name="is_sellable" val="false" />
		<set name="is_depositable" val="false" />
		<set name="is_stackable" val="true" />
		<set name="is_questitem" val="true" />
	</item>
	<item id="2650" type="EtcItem" name="泰瑞的信">
		<set name="icon" val="icon.etc_letter_blue_i00" />
		<set name="immediate_effect" val="1" />
		<set name="material" val="steel" />
		<set name="is_tradable" val="false" />
		<set name="is_dropable" val="false" />
		<set name="is_sellable" val="false" />
		<set name="is_depositable" val="false" />
		<set name="is_stackable" val="true" />
		<set name="is_questitem" val="true" />
	</item>
	<item id="2651" type="EtcItem" name="畢克特的信">
		<set name="icon" val="icon.etc_letter_red_i00" />
		<set name="immediate_effect" val="1" />
		<set name="material" val="steel" />
		<set name="is_tradable" val="false" />
		<set name="is_dropable" val="false" />
		<set name="is_sellable" val="false" />
		<set name="is_depositable" val="false" />
		<set name="is_stackable" val="true" />
		<set name="is_questitem" val="true" />
	</item>
	<item id="2652" type="EtcItem" name="鷹眼的信">
		<set name="icon" val="icon.etc_letter_white_i00" />
		<set name="immediate_effect" val="1" />
		<set name="material" val="steel" />
		<set name="is_tradable" val="false" />
		<set name="is_dropable" val="false" />
		<set name="is_sellable" val="false" />
		<set name="is_depositable" val="false" />
		<set name="is_stackable" val="true" />
		<set name="is_questitem" val="true" />
	</item>
	<item id="2653" type="EtcItem" name="神祕的魔精石">
		<set name="icon" val="icon.etc_crystal_blue_i00" />
		<set name="immediate_effect" val="1" />
		<set name="material" val="steel" />
		<set name="is_tradable" val="false" />
		<set name="is_dropable" val="false" />
		<set name="is_sellable" val="false" />
		<set name="is_depositable" val="false" />
		<set name="is_stackable" val="true" />
		<set name="is_questitem" val="true" />
	</item>
	<item id="2654" type="EtcItem" name="豺狼魔精石">
		<set name="icon" val="icon.etc_crystal_red_i00" />
		<set name="immediate_effect" val="1" />
		<set name="material" val="steel" />
		<set name="is_tradable" val="false" />
		<set name="is_dropable" val="false" />
		<set name="is_sellable" val="false" />
		<set name="is_depositable" val="false" />
		<set name="is_stackable" val="true" />
		<set name="is_questitem" val="true" />
	</item>
	<item id="2655" type="EtcItem" name="土瑞克魔精石">
		<set name="icon" val="icon.etc_crystal_silver_i00" />
		<set name="immediate_effect" val="1" />
		<set name="material" val="steel" />
		<set name="is_tradable" val="false" />
		<set name="is_dropable" val="false" />
		<set name="is_sellable" val="false" />
		<set name="is_depositable" val="false" />
		<set name="is_stackable" val="true" />
		<set name="is_questitem" val="true" />
	</item>
	<item id="2656" type="EtcItem" name="螞蟻魔精石">
		<set name="icon" val="icon.etc_crystal_white_i00" />
		<set name="immediate_effect" val="1" />
		<set name="material" val="steel" />
		<set name="is_tradable" val="false" />
		<set name="is_dropable" val="false" />
		<set name="is_sellable" val="false" />
		<set name="is_depositable" val="false" />
		<set name="is_stackable" val="true" />
		<set name="is_questitem" val="true" />
	</item>
	<item id="2657" type="EtcItem" name="突倫克食人妖魔精石">
		<set name="icon" val="icon.etc_crystal_gold_i00" />
		<set name="immediate_effect" val="1" />
		<set name="material" val="steel" />
		<set name="is_tradable" val="false" />
		<set name="is_dropable" val="false" />
		<set name="is_sellable" val="false" />
		<set name="is_depositable" val="false" />
		<set name="is_stackable" val="true" />
		<set name="is_questitem" val="true" />
	</item>
	<item id="2658" type="EtcItem" name="泰瑞的箱子">
		<set name="icon" val="icon.etc_jewel_box_i00" />
		<set name="immediate_effect" val="1" />
		<set name="material" val="steel" />
		<set name="is_tradable" val="false" />
		<set name="is_dropable" val="false" />
		<set name="is_sellable" val="false" />
		<set name="is_depositable" val="false" />
		<set name="is_stackable" val="true" />
		<set name="is_questitem" val="true" />
	</item>
	<item id="2659" type="EtcItem" name="畢克特的請求">
		<set name="icon" val="icon.etc_scroll_of_enchant_armor_i01" />
		<set name="immediate_effect" val="1" />
		<set name="material" val="steel" />
		<set name="is_tradable" val="false" />
		<set name="is_dropable" val="false" />
		<set name="is_sellable" val="false" />
		<set name="is_depositable" val="false" />
		<set name="is_stackable" val="true" />
		<set name="is_questitem" val="true" />
	</item>
	<item id="2660" type="EtcItem" name="梅杜莎鱗片">
		<set name="icon" val="icon.etc_parasite_i00" />
		<set name="immediate_effect" val="1" />
		<set name="material" val="steel" />
		<set name="is_tradable" val="false" />
		<set name="is_dropable" val="false" />
		<set name="is_sellable" val="false" />
		<set name="is_depositable" val="false" />
		<set name="is_stackable" val="true" />
		<set name="is_questitem" val="true" />
	</item>
	<item id="2661" type="EtcItem" name="賽勒諾斯魔精石">
		<set name="icon" val="icon.etc_crystal_green_i00" />
		<set name="immediate_effect" val="1" />
		<set name="material" val="steel" />
		<set name="is_tradable" val="false" />
		<set name="is_dropable" val="false" />
		<set name="is_sellable" val="false" />
		<set name="is_depositable" val="false" />
		<set name="is_stackable" val="true" />
		<set name="is_questitem" val="true" />
	</item>
	<item id="2662" type="EtcItem" name="分析的要求">
		<set name="icon" val="icon.etc_recipe_blue_i00" />
		<set name="immediate_effect" val="1" />
		<set name="material" val="steel" />
		<set name="is_tradable" val="false" />
		<set name="is_dropable" val="false" />
		<set name="is_sellable" val="false" />
		<set name="is_depositable" val="false" />
		<set name="is_stackable" val="true" />
		<set name="is_questitem" val="true" />
	</item>
	<item id="2663" type="EtcItem" name="瑪莉娜的信">
		<set name="icon" val="icon.etc_piece_of_paper_white_i00" />
		<set name="immediate_effect" val="1" />
		<set name="material" val="steel" />
		<set name="is_tradable" val="false" />
		<set name="is_dropable" val="false" />
		<set name="is_sellable" val="false" />
		<set name="is_depositable" val="false" />
		<set name="is_stackable" val="true" />
		<set name="is_questitem" val="true" />
	</item>
	<item id="2664" type="EtcItem" name="實驗工具">
		<set name="icon" val="icon.etc_squares_wood_i00" />
		<set name="immediate_effect" val="1" />
		<set name="material" val="steel" />
		<set name="is_tradable" val="false" />
		<set name="is_dropable" val="false" />
		<set name="is_sellable" val="false" />
		<set name="is_depositable" val="false" />
		<set name="is_stackable" val="true" />
		<set name="is_questitem" val="true" />
	</item>
	<item id="2665" type="EtcItem" name="分析的結果">
		<set name="icon" val="icon.etc_recipe_red_i00" />
		<set name="immediate_effect" val="1" />
		<set name="material" val="steel" />
		<set name="is_tradable" val="false" />
		<set name="is_dropable" val="false" />
		<set name="is_sellable" val="false" />
		<set name="is_depositable" val="false" />
		<set name="is_stackable" val="true" />
		<set name="is_questitem" val="true" />
	</item>
	<item id="2666" type="EtcItem" name="泰瑞的單子">
		<set name="icon" val="icon.etc_scroll_of_enchant_weapon_i01" />
		<set name="immediate_effect" val="1" />
		<set name="material" val="steel" />
		<set name="is_tradable" val="false" />
		<set name="is_dropable" val="false" />
		<set name="is_sellable" val="false" />
		<set name="is_depositable" val="false" />
		<set name="is_stackable" val="true" />
		<set name="is_questitem" val="true" />
	</item>
	<item id="2667" type="EtcItem" name="宿主的清單">
		<set name="icon" val="icon.etc_piece_of_paper_black_i00" />
		<set name="immediate_effect" val="1" />
		<set name="material" val="steel" />
		<set name="is_tradable" val="false" />
		<set name="is_dropable" val="false" />
		<set name="is_sellable" val="false" />
		<set name="is_depositable" val="false" />
		<set name="is_stackable" val="true" />
		<set name="is_questitem" val="true" />
	</item>
	<item id="2668" type="EtcItem" name="深淵魔精石">
		<set name="icon" val="icon.etc_crystal_blue_i00" />
		<set name="immediate_effect" val="1" />
		<set name="material" val="steel" />
		<set name="is_tradable" val="false" />
		<set name="is_dropable" val="false" />
		<set name="is_sellable" val="false" />
		<set name="is_depositable" val="false" />
		<set name="is_stackable" val="true" />
		<set name="is_questitem" val="true" />
	</item>
	<item id="2669" type="EtcItem" name="深淵魔精石">
		<set name="icon" val="icon.etc_crystal_silver_i00" />
		<set name="immediate_effect" val="1" />
		<set name="material" val="steel" />
		<set name="is_tradable" val="false" />
		<set name="is_dropable" val="false" />
		<set name="is_sellable" val="false" />
		<set name="is_depositable" val="false" />
		<set name="is_stackable" val="true" />
		<set name="is_questitem" val="true" />
	</item>
	<item id="2670" type="EtcItem" name="深淵魔精石">
		<set name="icon" val="icon.etc_crystal_white_i00" />
		<set name="immediate_effect" val="1" />
		<set name="material" val="steel" />
		<set name="is_tradable" val="false" />
		<set name="is_dropable" val="false" />
		<set name="is_sellable" val="false" />
		<set name="is_depositable" val="false" />
		<set name="is_stackable" val="true" />
		<set name="is_questitem" val="true" />
	</item>
	<item id="2671" type="EtcItem" name="深淵魔精石">
		<set name="icon" val="icon.etc_crystal_green_i00" />
		<set name="immediate_effect" val="1" />
		<set name="material" val="steel" />
		<set name="is_tradable" val="false" />
		<set name="is_dropable" val="false" />
		<set name="is_sellable" val="false" />
		<set name="is_depositable" val="false" />
		<set name="is_stackable" val="true" />
		<set name="is_questitem" val="true" />
	</item>
	<item id="2672" type="EtcItem" name="泰瑞的報告">
		<set name="icon" val="icon.etc_scroll_of_enchant_weapon_i00" />
		<set name="immediate_effect" val="1" />
		<set name="material" val="steel" />
		<set name="is_tradable" val="false" />
		<set name="is_dropable" val="false" />
		<set name="is_sellable" val="false" />
		<set name="is_depositable" val="false" />
		<set name="is_stackable" val="true" />
		<set name="is_questitem" val="true" />
	</item>
	<item id="2673" type="EtcItem" name="巡守者標章">
		<set name="icon" val="icon.etc_jewel_green_i00" />
		<set name="immediate_effect" val="1" />
		<set name="material" val="steel" />
		<set name="is_tradable" val="false" />
		<set name="is_dropable" val="false" />
		<set name="is_sellable" val="false" />
		<set name="is_depositable" val="false" />
		<set name="is_stackable" val="true" />
		<set name="is_questitem" val="true" />
	</item>
	<item id="2674" type="EtcItem" name="探求者標章">
		<set name="icon" val="icon.etc_jewel_blue_i00" />
		<set name="immediate_effect" val="1" />
		<set name="material" val="steel" />
		<set name="is_tradable" val="false" />
		<set name="is_dropable" val="false" />
		<set name="is_sellable" val="false" />
		<set name="is_depositable" val="false" />
		<set name="is_stackable" val="true" />
		<set name="is_questitem" val="true" />
	</item>
	<item id="2675" type="EtcItem" name="米麗恩的印章">
		<set name="icon" val="icon.shield_shield_of_mana_i00" />
		<set name="immediate_effect" val="1" />
		<set name="material" val="steel" />
		<set name="is_tradable" val="false" />
		<set name="is_dropable" val="false" />
		<set name="is_sellable" val="false" />
		<set name="is_depositable" val="false" />
		<set name="is_stackable" val="true" />
		<set name="is_questitem" val="true" />
	</item>
	<item id="2676" type="EtcItem" name="米麗恩的印章">
		<set name="icon" val="icon.shield_shield_of_pledge_i00" />
		<set name="immediate_effect" val="1" />
		<set name="material" val="steel" />
		<set name="is_tradable" val="false" />
		<set name="is_dropable" val="false" />
		<set name="is_sellable" val="false" />
		<set name="is_depositable" val="false" />
		<set name="is_stackable" val="true" />
		<set name="is_questitem" val="true" />
	</item>
	<item id="2677" type="EtcItem" name="米麗恩的印章">
		<set name="icon" val="icon.shield_round_shield_i00" />
		<set name="immediate_effect" val="1" />
		<set name="material" val="steel" />
		<set name="is_tradable" val="false" />
		<set name="is_dropable" val="false" />
		<set name="is_sellable" val="false" />
		<set name="is_depositable" val="false" />
		<set name="is_stackable" val="true" />
		<set name="is_questitem" val="true" />
	</item>
	<item id="2678" type="EtcItem" name="米麗恩的指示">
		<set name="icon" val="icon.etc_scroll_gray_i00" />
		<set name="immediate_effect" val="1" />
		<set name="material" val="steel" />
		<set name="is_tradable" val="false" />
		<set name="is_dropable" val="false" />
		<set name="is_sellable" val="false" />
		<set name="is_depositable" val="false" />
		<set name="is_stackable" val="true" />
		<set name="is_questitem" val="true" />
	</item>
	<item id="2679" type="EtcItem" name="瑪利亞的信">
		<set name="icon" val="icon.etc_letter_blue_i00" />
		<set name="immediate_effect" val="1" />
		<set name="material" val="steel" />
		<set name="is_tradable" val="false" />
		<set name="is_dropable" val="false" />
		<set name="is_sellable" val="false" />
		<set name="is_depositable" val="false" />
		<set name="is_stackable" val="true" />
		<set name="is_questitem" val="true" />
	</item>
	<item id="2680" type="EtcItem" name="瑪利亞的信">
		<set name="icon" val="icon.etc_letter_red_i00" />
		<set name="immediate_effect" val="1" />
		<set name="material" val="steel" />
		<set name="is_tradable" val="false" />
		<set name="is_dropable" val="false" />
		<set name="is_sellable" val="false" />
		<set name="is_depositable" val="false" />
		<set name="is_stackable" val="true" />
		<set name="is_questitem" val="true" />
	</item>
	<item id="2681" type="EtcItem" name="盧卡斯的信">
		<set name="icon" val="icon.etc_letter_white_i00" />
		<set name="immediate_effect" val="1" />
		<set name="material" val="steel" />
		<set name="is_tradable" val="false" />
		<set name="is_dropable" val="false" />
		<set name="is_sellable" val="false" />
		<set name="is_depositable" val="false" />
		<set name="is_stackable" val="true" />
		<set name="is_questitem" val="true" />
	</item>
	<item id="2682" type="EtcItem" name="露希拉的手提包">
		<set name="icon" val="icon.etc_pouch_yellow_i00" />
		<set name="immediate_effect" val="1" />
		<set name="material" val="steel" />
		<set name="is_tradable" val="false" />
		<set name="is_dropable" val="false" />
		<set name="is_sellable" val="false" />
		<set name="is_depositable" val="false" />
		<set name="is_stackable" val="true" />
		<set name="is_questitem" val="true" />
	</item>
	<item id="2683" type="EtcItem" name="克瑞塔的信">
		<set name="icon" val="icon.etc_letter_blue_i00" />
		<set name="immediate_effect" val="1" />
		<set name="material" val="steel" />
		<set name="is_tradable" val="false" />
		<set name="is_dropable" val="false" />
		<set name="is_sellable" val="false" />
		<set name="is_depositable" val="false" />
		<set name="is_stackable" val="true" />
		<set name="is_questitem" val="true" />
	</item>
	<item id="2684" type="EtcItem" name="克瑞塔的繪畫">
		<set name="icon" val="icon.etc_scroll_of_enchant_armor_i00" />
		<set name="immediate_effect" val="1" />
		<set name="material" val="steel" />
		<set name="is_tradable" val="false" />
		<set name="is_dropable" val="false" />
		<set name="is_sellable" val="false" />
		<set name="is_depositable" val="false" />
		<set name="is_stackable" val="true" />
		<set name="is_questitem" val="true" />
	</item>
	<item id="2685" type="EtcItem" name="克瑞塔的繪畫">
		<set name="icon" val="icon.etc_scroll_of_resurrection_i00" />
		<set name="immediate_effect" val="1" />
		<set name="material" val="steel" />
		<set name="is_tradable" val="false" />
		<set name="is_dropable" val="false" />
		<set name="is_sellable" val="false" />
		<set name="is_depositable" val="false" />
		<set name="is_stackable" val="true" />
		<set name="is_questitem" val="true" />
	</item>
	<item id="2686" type="EtcItem" name="克瑞塔的繪畫">
		<set name="icon" val="icon.etc_scroll_of_return_i00" />
		<set name="immediate_effect" val="1" />
		<set name="material" val="steel" />
		<set name="is_tradable" val="false" />
		<set name="is_dropable" val="false" />
		<set name="is_sellable" val="false" />
		<set name="is_depositable" val="false" />
		<set name="is_stackable" val="true" />
		<set name="is_questitem" val="true" />
	</item>
	<item id="2687" type="EtcItem" name="棕色卷軸殘片">
		<set name="icon" val="icon.etc_map_piece_yellow_i00" />
		<set name="immediate_effect" val="1" />
		<set name="material" val="steel" />
		<set name="is_tradable" val="false" />
		<set name="is_dropable" val="false" />
		<set name="is_sellable" val="false" />
		<set name="is_depositable" val="false" />
		<set name="is_stackable" val="true" />
		<set name="is_questitem" val="true" />
	</item>
	<item id="2688" type="EtcItem" name="純淨水晶">
		<set name="icon" val="icon.etc_gem_clear_i00" />
		<set name="immediate_effect" val="1" />
		<set name="material" val="steel" />
		<set name="is_tradable" val="false" />
		<set name="is_dropable" val="false" />
		<set name="is_sellable" val="false" />
		<set name="is_depositable" val="false" />
		<set name="is_stackable" val="true" />
		<set name="is_questitem" val="true" />
	</item>
	<item id="2689" type="EtcItem" name="大神官標章">
		<set name="icon" val="icon.shield_sages_shield_i01" />
		<set name="immediate_effect" val="1" />
		<set name="material" val="steel" />
		<set name="is_tradable" val="false" />
		<set name="is_dropable" val="false" />
		<set name="is_sellable" val="false" />
		<set name="is_depositable" val="false" />
		<set name="is_stackable" val="true" />
		<set name="is_questitem" val="true" />
	</item>
	<item id="2690" type="EtcItem" name="大巫師標章">
		<set name="icon" val="icon.shield_doom_shield_i00" />
		<set name="immediate_effect" val="1" />
		<set name="material" val="steel" />
		<set name="is_tradable" val="false" />
		<set name="is_dropable" val="false" />
		<set name="is_sellable" val="false" />
		<set name="is_depositable" val="false" />
		<set name="is_stackable" val="true" />
		<set name="is_questitem" val="true" />
	</item>
	<item id="2691" type="EtcItem" name="賢者標章">
		<set name="icon" val="icon.shield_another_worlds_shield_i01" />
		<set name="immediate_effect" val="1" />
		<set name="material" val="steel" />
		<set name="is_tradable" val="false" />
		<set name="is_dropable" val="false" />
		<set name="is_sellable" val="false" />
		<set name="is_depositable" val="false" />
		<set name="is_stackable" val="true" />
		<set name="is_questitem" val="true" />
	</item>
	<item id="2692" type="EtcItem" name="錫爾巴銀的信">
		<set name="icon" val="icon.etc_piece_of_paper_gray_i00" />
		<set name="immediate_effect" val="1" />
		<set name="material" val="steel" />
		<set name="is_tradable" val="false" />
		<set name="is_dropable" val="false" />
		<set name="is_sellable" val="false" />
		<set name="is_depositable" val="false" />
		<set name="is_stackable" val="true" />
		<set name="is_questitem" val="true" />
	</item>
	<item id="2693" type="EtcItem" name="錫爾巴銀的憑證">
		<set name="icon" val="icon.etc_coins_blue_i00" />
		<set name="immediate_effect" val="1" />
		<set name="material" val="steel" />
		<set name="is_tradable" val="false" />
		<set name="is_dropable" val="false" />
		<set name="is_sellable" val="false" />
		<set name="is_depositable" val="false" />
		<set name="is_stackable" val="true" />
		<set name="is_questitem" val="true" />
	</item>
	<item id="2694" type="EtcItem" name="久黎克的清單">
		<set name="icon" val="icon.etc_piece_of_paper_black_i00" />
		<set name="immediate_effect" val="1" />
		<set name="material" val="steel" />
		<set name="is_tradable" val="false" />
		<set name="is_dropable" val="false" />
		<set name="is_sellable" val="false" />
		<set name="is_depositable" val="false" />
		<set name="is_stackable" val="true" />
		<set name="is_questitem" val="true" />
	</item>
	<item id="2695" type="EtcItem" name="搜索者的皮">
		<set name="icon" val="icon.etc_leather_yellow_i00" />
		<set name="immediate_effect" val="1" />
		<set name="material" val="steel" />
		<set name="is_tradable" val="false" />
		<set name="is_dropable" val="false" />
		<set name="is_sellable" val="false" />
		<set name="is_depositable" val="false" />
		<set name="is_stackable" val="true" />
		<set name="is_questitem" val="true" />
	</item>
	<item id="2696" type="EtcItem" name="巫師項鍊">
		<set name="icon" val="icon.etc_totem_necklace_red_i00" />
		<set name="immediate_effect" val="1" />
		<set name="material" val="steel" />
		<set name="is_tradable" val="false" />
		<set name="is_dropable" val="false" />
		<set name="is_sellable" val="false" />
		<set name="is_depositable" val="false" />
		<set name="is_stackable" val="true" />
		<set name="is_questitem" val="true" />
	</item>
	<item id="2697" type="EtcItem" name="束縛靈的頭皮">
		<set name="icon" val="icon.etc_leather_brown_i00" />
		<set name="immediate_effect" val="1" />
		<set name="material" val="steel" />
		<set name="is_tradable" val="false" />
		<set name="is_dropable" val="false" />
		<set name="is_sellable" val="false" />
		<set name="is_depositable" val="false" />
		<set name="is_stackable" val="true" />
		<set name="is_questitem" val="true" />
	</item>
	<item id="2698" type="EtcItem" name="大巫師久黎克的標章">
		<set name="icon" val="icon.etc_coins_gold_i00" />
		<set name="immediate_effect" val="1" />
		<set name="material" val="steel" />
		<set name="is_tradable" val="false" />
		<set name="is_dropable" val="false" />
		<set name="is_sellable" val="false" />
		<set name="is_depositable" val="false" />
		<set name="is_stackable" val="true" />
		<set name="is_questitem" val="true" />
	</item>
	<item id="2699" type="EtcItem" name="克洛諾斯的信">
		<set name="icon" val="icon.etc_letter_red_i00" />
		<set name="immediate_effect" val="1" />
		<set name="material" val="steel" />
		<set name="is_tradable" val="false" />
		<set name="is_dropable" val="false" />
		<set name="is_sellable" val="false" />
		<set name="is_depositable" val="false" />
		<set name="is_stackable" val="true" />
		<set name="is_questitem" val="true" />
	</item>
</list>
