<?xml version="1.0" encoding="UTF-8"?>
<list>
	<skill id="2900" levels="1" name="原始藥草-虐殺者">
		<set name="staticHitTime" val="true" />
		<set name="target" val="TARGET_SELF" />
		<set name="skillType" val="BUFF" />
		<set name="operateType" val="OP_ACTIVE" />
		<set name="isPotion" val="true" />
		<set name="buffDuration" val="60000" />
		<set name="reuseDelay" val="2000" />
		<cond msgId="113" addName="1">
			<player level="78" />
		</cond>
		<for>
			<effect name="Buff" time="60" val="0" stackOrder="1" stackType="signal_c" />
		</for>
	</skill>
	<skill id="2901" levels="1" name="原始藥草-不滅者">
		<set name="staticHitTime" val="true" />
		<set name="target" val="TARGET_SELF" />
		<set name="skillType" val="BUFF" />
		<set name="operateType" val="OP_ACTIVE" />
		<set name="isPotion" val="true" />
		<set name="buffDuration" val="60000" />
		<set name="reuseDelay" val="2000" />
		<cond msgId="113" addName="1">
			<player level="78" />
		</cond>
		<for>
			<effect name="Invincible" time="60" val="0" stackOrder="1" stackType="pd_up_special" />
		</for>
	</skill>
	<skill id="2902" levels="1" name="原始藥草-終結者">
		<set name="staticHitTime" val="true" />
		<set name="target" val="TARGET_SELF" />
		<set name="skillType" val="BUFF" />
		<set name="operateType" val="OP_ACTIVE" />
		<set name="isPotion" val="true" />
		<set name="buffDuration" val="60000" />
		<set name="reuseDelay" val="2000" />
		<cond msgId="113" addName="1">
			<player level="78" />
		</cond>
		<for>
			<effect name="Buff" time="60" val="0" stackOrder="4" stackType="casting_time_down">
				<mul order="0x30" stat="mAtkSpd" val="1.7" />
			</effect>
		</for>
	</skill>
	<skill id="2903" levels="1" name="原始藥草-引導者">
		<set name="staticHitTime" val="true" />
		<set name="target" val="TARGET_SELF" />
		<set name="skillType" val="BUFF" />
		<set name="operateType" val="OP_ACTIVE" />
		<set name="isPotion" val="true" />
		<set name="buffDuration" val="60000" />
		<set name="reuseDelay" val="2000" />
		<cond msgId="113" addName="1">
			<player level="78" />
		</cond>
		<for>
			<effect name="Buff" time="60" val="0" stackOrder="4" stackType="speed_up_special">
				<add order="0x40" stat="runSpd" val="250" />
			</effect>
		</for>
	</skill>
	<skill id="2904" levels="1" name="守護靈魂的加護">
		<set name="target" val="TARGET_NONE" />
		<set name="skillType" val="NOTDONE" />
		<set name="reuseDelay" val="2000" />
		<set name="operateType" val="OP_PASSIVE" />
	</skill>
	<skill id="2905" levels="1" name="成長促進劑">
		<set name="itemConsumeCount" val="1" />
		<set name="target" val="TARGET_ONE" />
		<set name="skillType" val="DEBUFF" />
		<set name="isDebuff" val="true" />
		<set name="operateType" val="OP_ACTIVE" />
		<set name="hitTime" val="4000" />
		<set name="staticHitTime" val="true" />
		<set name="reuseDelay" val="2000" />
		<cond msgId="113" addName="1">
			<and>
				<not>
					<target mindistance="200" />
				</not>
				<target npcId="18793,18794,18795,18796,18797,18798" />
			</and>
		</cond>
	</skill>
	<skill id="2906" levels="1" name="孵化促進劑">
		<set name="target" val="TARGET_NONE" />
		<set name="skillType" val="NOTDONE" />
		<set name="reuseDelay" val="2000" />
		<set name="operateType" val="OP_PASSIVE" />
	</skill>
	<skill id="2907" levels="1" name="戰場用生命靈藥">
		<set name="target" val="TARGET_NONE" />
		<set name="skillType" val="NOTDONE" />
		<set name="reuseDelay" val="600000" />
		<set name="operateType" val="OP_PASSIVE" />
	</skill>
	<skill id="2908" levels="1" name="戰場用精神靈藥">
		<set name="target" val="TARGET_NONE" />
		<set name="skillType" val="NOTDONE" />
		<set name="reuseDelay" val="600000" />
		<set name="operateType" val="OP_PASSIVE" />
	</skill>
	<skill id="2909" levels="1" name="戰場用鬥志靈藥">
		<set name="target" val="TARGET_NONE" />
		<set name="skillType" val="NOTDONE" />
		<set name="reuseDelay" val="600000" />
		<set name="operateType" val="OP_PASSIVE" />
	</skill>
	<skill id="2910" levels="1" name="苦痛的骸骨鑰匙">
		<set name="target" val="TARGET_NONE" />
		<set name="skillType" val="NOTDONE" />
		<set name="operateType" val="OP_PASSIVE" />
	</skill>
	<skill id="2911" levels="1" name="侵蝕的骸骨鑰匙">
		<set name="target" val="TARGET_NONE" />
		<set name="skillType" val="NOTDONE" />
		<set name="operateType" val="OP_PASSIVE" />
	</skill>
	<skill id="2912" levels="1" name="心臟部的骸骨鑰匙">
		<set name="target" val="TARGET_NONE" />
		<set name="skillType" val="NOTDONE" />
		<set name="operateType" val="OP_PASSIVE" />
	</skill>
	<skill id="2913" levels="1" name="靈魂抽取">
		<set name="target" val="TARGET_NONE" />
		<set name="skillType" val="NOTDONE" />
		<set name="reuseDelay" val="60000" />
		<set name="operateType" val="OP_PASSIVE" />
	</skill>
	<skill id="2914" levels="2" name="裝備套裝 10日/組">
		<set name="target" val="TARGET_NONE" />
		<set name="skillType" val="NOTDONE" />
		<set name="reuseDelay" val="10000" />
		<set name="operateType" val="OP_PASSIVE" />
	</skill>
	<skill id="2915" levels="1" name="五彩繽紛的礦石">
		<set name="itemConsumeCount" val="1" />
		<set name="target" val="TARGET_SELF" />
		<set name="hitTime" val="20000" />
		<set name="reuseDelay" val="10000" />
		<set name="skillType" val="TELEPORT" />
		<set name="teleCoords" val="89417,-44506,-2126" />
		<set name="operateType" val="OP_ACTIVE" />
	</skill>
	<skill id="2916" levels="1" name="高濃縮強化寵物飼料">
		<set name="target" val="TARGET_NONE" />
		<set name="skillType" val="NOTDONE" />
		<set name="operateType" val="OP_PASSIVE" />
	</skill>
	<skill id="2917" levels="1" name="大型司塔卡拓的繭">
		<set name="itemConsumeCount" val="1" />
		<set name="target" val="TARGET_SELF" />
		<set name="skillType" val="EXTRACTABLE" />
		<set name="operateType" val="OP_ACTIVE" />
		<cond msgId="129">
			<and>
				<player invSize="10" />
				<player weight="80" />
			</and>
		</cond>
	</skill>
	<skill id="2918" levels="1" name="小型司塔卡拓的繭">
		<set name="itemConsumeCount" val="1" />
		<set name="target" val="TARGET_SELF" />
		<set name="skillType" val="EXTRACTABLE" />
		<set name="operateType" val="OP_ACTIVE" />
		<cond msgId="129">
			<and>
				<player invSize="10" />
				<player weight="80" />
			</and>
		</cond>
	</skill>
	<skill id="2919" levels="1" name="古代的羊皮紙">
		<set name="itemConsumeCount" val="1" />
		<set name="target" val="TARGET_SELF" />
		<set name="skillType" val="EXTRACTABLE" />
		<set name="operateType" val="OP_ACTIVE" />
		<cond msgId="129">
			<and>
				<player invSize="10" />
				<player weight="80" />
			</and>
		</cond>
	</skill>
	<skill id="2920" levels="1" name="下巨人古書籍">
		<set name="itemConsumeCount" val="1" />
		<set name="target" val="TARGET_SELF" />
		<set name="skillType" val="EXTRACTABLE" />
		<set name="operateType" val="OP_ACTIVE" />
		<cond msgId="129">
			<and>
				<player invSize="10" />
				<player weight="80" />
			</and>
		</cond>
	</skill>
	<skill id="2921" levels="1" name="古魯丁補給箱-魔法別針">
		<set name="itemConsumeCount" val="1" />
		<set name="target" val="TARGET_SELF" />
		<set name="skillType" val="EXTRACTABLE" />
		<set name="operateType" val="OP_ACTIVE" />
		<cond msgId="129">
			<and>
				<player invSize="10" />
				<player weight="80" />
			</and>
		</cond>
	</skill>
	<skill id="2922" levels="1" name="狄恩補給箱-魔法別針">
		<set name="itemConsumeCount" val="1" />
		<set name="target" val="TARGET_SELF" />
		<set name="skillType" val="EXTRACTABLE" />
		<set name="operateType" val="OP_ACTIVE" />
		<cond msgId="129">
			<and>
				<player invSize="10" />
				<player weight="80" />
			</and>
		</cond>
	</skill>
	<skill id="2923" levels="1" name="奇岩補給箱-魔法別針">
		<set name="itemConsumeCount" val="1" />
		<set name="target" val="TARGET_SELF" />
		<set name="skillType" val="EXTRACTABLE" />
		<set name="operateType" val="OP_ACTIVE" />
		<cond msgId="129">
			<and>
				<player invSize="10" />
				<player weight="80" />
			</and>
		</cond>
	</skill>
	<skill id="2924" levels="1" name="歐瑞補給箱-魔法別針">
		<set name="itemConsumeCount" val="1" />
		<set name="target" val="TARGET_SELF" />
		<set name="skillType" val="EXTRACTABLE" />
		<set name="operateType" val="OP_ACTIVE" />
		<cond msgId="129">
			<and>
				<player invSize="10" />
				<player weight="80" />
			</and>
		</cond>
	</skill>
	<skill id="2925" levels="1" name="亞丁補給箱-魔法別針">
		<set name="itemConsumeCount" val="1" />
		<set name="target" val="TARGET_SELF" />
		<set name="skillType" val="EXTRACTABLE" />
		<set name="operateType" val="OP_ACTIVE" />
		<cond msgId="129">
			<and>
				<player invSize="10" />
				<player weight="80" />
			</and>
		</cond>
	</skill>
	<skill id="2926" levels="1" name="因納得立補給箱-魔法別針">
		<set name="itemConsumeCount" val="1" />
		<set name="target" val="TARGET_SELF" />
		<set name="skillType" val="EXTRACTABLE" />
		<set name="operateType" val="OP_ACTIVE" />
		<cond msgId="129">
			<and>
				<player invSize="10" />
				<player weight="80" />
			</and>
		</cond>
	</skill>
	<skill id="2927" levels="1" name="高達特補給箱-魔法別針">
		<set name="itemConsumeCount" val="1" />
		<set name="target" val="TARGET_SELF" />
		<set name="skillType" val="EXTRACTABLE" />
		<set name="operateType" val="OP_ACTIVE" />
		<cond msgId="129">
			<and>
				<player invSize="10" />
				<player weight="80" />
			</and>
		</cond>
	</skill>
	<skill id="2928" levels="1" name="魯因補給箱-魔法別針">
		<set name="itemConsumeCount" val="1" />
		<set name="target" val="TARGET_SELF" />
		<set name="skillType" val="EXTRACTABLE" />
		<set name="operateType" val="OP_ACTIVE" />
		<cond msgId="129">
			<and>
				<player invSize="10" />
				<player weight="80" />
			</and>
		</cond>
	</skill>
	<skill id="2929" levels="1" name="修加特補給箱-魔法別針">
		<set name="itemConsumeCount" val="1" />
		<set name="target" val="TARGET_SELF" />
		<set name="skillType" val="EXTRACTABLE" />
		<set name="operateType" val="OP_ACTIVE" />
		<cond msgId="129">
			<and>
				<player invSize="10" />
				<player weight="80" />
			</and>
		</cond>
	</skill>
	<skill id="2930" levels="1" name="古魯丁補給箱-魔法小袋">
		<set name="itemConsumeCount" val="1" />
		<set name="target" val="TARGET_SELF" />
		<set name="skillType" val="EXTRACTABLE" />
		<set name="operateType" val="OP_ACTIVE" />
		<cond msgId="129">
			<and>
				<player invSize="10" />
				<player weight="80" />
			</and>
		</cond>
	</skill>
	<skill id="2931" levels="1" name="狄恩補給箱-魔法小袋">
		<set name="itemConsumeCount" val="1" />
		<set name="target" val="TARGET_SELF" />
		<set name="skillType" val="EXTRACTABLE" />
		<set name="operateType" val="OP_ACTIVE" />
		<cond msgId="129">
			<and>
				<player invSize="10" />
				<player weight="80" />
			</and>
		</cond>
	</skill>
	<skill id="2932" levels="1" name="奇岩補給箱-魔法小袋">
		<set name="itemConsumeCount" val="1" />
		<set name="target" val="TARGET_SELF" />
		<set name="skillType" val="EXTRACTABLE" />
		<set name="operateType" val="OP_ACTIVE" />
		<cond msgId="129">
			<and>
				<player invSize="10" />
				<player weight="80" />
			</and>
		</cond>
	</skill>
	<skill id="2933" levels="1" name="歐瑞補給箱-魔法小袋">
		<set name="itemConsumeCount" val="1" />
		<set name="target" val="TARGET_SELF" />
		<set name="skillType" val="EXTRACTABLE" />
		<set name="operateType" val="OP_ACTIVE" />
		<cond msgId="129">
			<and>
				<player invSize="10" />
				<player weight="80" />
			</and>
		</cond>
	</skill>
	<skill id="2934" levels="1" name="亞丁補給箱-魔法小袋">
		<set name="itemConsumeCount" val="1" />
		<set name="target" val="TARGET_SELF" />
		<set name="skillType" val="EXTRACTABLE" />
		<set name="operateType" val="OP_ACTIVE" />
		<cond msgId="129">
			<and>
				<player invSize="10" />
				<player weight="80" />
			</and>
		</cond>
	</skill>
	<skill id="2935" levels="1" name="因納得立補給箱-魔法小袋">
		<set name="itemConsumeCount" val="1" />
		<set name="target" val="TARGET_SELF" />
		<set name="skillType" val="EXTRACTABLE" />
		<set name="operateType" val="OP_ACTIVE" />
		<cond msgId="129">
			<and>
				<player invSize="10" />
				<player weight="80" />
			</and>
		</cond>
	</skill>
	<skill id="2936" levels="1" name="高達特補給箱-魔法小袋">
		<set name="itemConsumeCount" val="1" />
		<set name="target" val="TARGET_SELF" />
		<set name="skillType" val="EXTRACTABLE" />
		<set name="operateType" val="OP_ACTIVE" />
		<cond msgId="129">
			<and>
				<player invSize="10" />
				<player weight="80" />
			</and>
		</cond>
	</skill>
	<skill id="2937" levels="1" name="魯因補給箱-魔法小袋">
		<set name="itemConsumeCount" val="1" />
		<set name="target" val="TARGET_SELF" />
		<set name="skillType" val="EXTRACTABLE" />
		<set name="operateType" val="OP_ACTIVE" />
		<cond msgId="129">
			<and>
				<player invSize="10" />
				<player weight="80" />
			</and>
		</cond>
	</skill>
	<skill id="2938" levels="1" name="修加特補給箱-魔法小袋">
		<set name="itemConsumeCount" val="1" />
		<set name="target" val="TARGET_SELF" />
		<set name="skillType" val="EXTRACTABLE" />
		<set name="operateType" val="OP_ACTIVE" />
		<cond msgId="129">
			<and>
				<player invSize="10" />
				<player weight="80" />
			</and>
		</cond>
	</skill>
	<skill id="2939" levels="1" name="古魯丁補給箱-腰帶">
		<set name="itemConsumeCount" val="1" />
		<set name="target" val="TARGET_SELF" />
		<set name="skillType" val="EXTRACTABLE" />
		<set name="operateType" val="OP_ACTIVE" />
		<cond msgId="129">
			<and>
				<player invSize="10" />
				<player weight="80" />
			</and>
		</cond>
	</skill>
	<skill id="2940" levels="1" name="狄恩補給箱-腰帶">
		<set name="itemConsumeCount" val="1" />
		<set name="target" val="TARGET_SELF" />
		<set name="skillType" val="EXTRACTABLE" />
		<set name="operateType" val="OP_ACTIVE" />
		<cond msgId="129">
			<and>
				<player invSize="10" />
				<player weight="80" />
			</and>
		</cond>
	</skill>
	<skill id="2941" levels="1" name="奇岩補給箱-腰帶">
		<set name="itemConsumeCount" val="1" />
		<set name="target" val="TARGET_SELF" />
		<set name="skillType" val="EXTRACTABLE" />
		<set name="operateType" val="OP_ACTIVE" />
		<cond msgId="129">
			<and>
				<player invSize="10" />
				<player weight="80" />
			</and>
		</cond>
	</skill>
	<skill id="2942" levels="1" name="歐瑞補給箱-腰帶">
		<set name="itemConsumeCount" val="1" />
		<set name="target" val="TARGET_SELF" />
		<set name="skillType" val="EXTRACTABLE" />
		<set name="operateType" val="OP_ACTIVE" />
		<cond msgId="129">
			<and>
				<player invSize="10" />
				<player weight="80" />
			</and>
		</cond>
	</skill>
	<skill id="2943" levels="1" name="亞丁補給箱-腰帶">
		<set name="itemConsumeCount" val="1" />
		<set name="target" val="TARGET_SELF" />
		<set name="skillType" val="EXTRACTABLE" />
		<set name="operateType" val="OP_ACTIVE" />
		<cond msgId="129">
			<and>
				<player invSize="10" />
				<player weight="80" />
			</and>
		</cond>
	</skill>
	<skill id="2944" levels="1" name="因納得立補給箱-腰帶">
		<set name="itemConsumeCount" val="1" />
		<set name="target" val="TARGET_SELF" />
		<set name="skillType" val="EXTRACTABLE" />
		<set name="operateType" val="OP_ACTIVE" />
		<cond msgId="129">
			<and>
				<player invSize="10" />
				<player weight="80" />
			</and>
		</cond>
	</skill>
	<skill id="2945" levels="1" name="高達特補給箱-腰帶">
		<set name="itemConsumeCount" val="1" />
		<set name="target" val="TARGET_SELF" />
		<set name="skillType" val="EXTRACTABLE" />
		<set name="operateType" val="OP_ACTIVE" />
		<cond msgId="129">
			<and>
				<player invSize="10" />
				<player weight="80" />
			</and>
		</cond>
	</skill>
	<skill id="2946" levels="1" name="魯因補給箱-腰帶">
		<set name="itemConsumeCount" val="1" />
		<set name="target" val="TARGET_SELF" />
		<set name="skillType" val="EXTRACTABLE" />
		<set name="operateType" val="OP_ACTIVE" />
		<cond msgId="129">
			<and>
				<player invSize="10" />
				<player weight="80" />
			</and>
		</cond>
	</skill>
	<skill id="2947" levels="1" name="修加特補給箱-腰帶">
		<set name="itemConsumeCount" val="1" />
		<set name="target" val="TARGET_SELF" />
		<set name="skillType" val="EXTRACTABLE" />
		<set name="operateType" val="OP_ACTIVE" />
		<cond msgId="129">
			<and>
				<player invSize="10" />
				<player weight="80" />
			</and>
		</cond>
	</skill>
	<skill id="2948" levels="1" name="古魯丁補給箱-魔法別針">
		<set name="itemConsumeCount" val="1" />
		<set name="target" val="TARGET_SELF" />
		<set name="skillType" val="EXTRACTABLE" />
		<set name="operateType" val="OP_ACTIVE" />
		<cond msgId="129">
			<and>
				<player invSize="10" />
				<player weight="80" />
			</and>
		</cond>
	</skill>
	<skill id="2949" levels="1" name="狄恩補給箱-魔法別針">
		<set name="itemConsumeCount" val="1" />
		<set name="target" val="TARGET_SELF" />
		<set name="skillType" val="EXTRACTABLE" />
		<set name="operateType" val="OP_ACTIVE" />
		<cond msgId="129">
			<and>
				<player invSize="10" />
				<player weight="80" />
			</and>
		</cond>
	</skill>
	<skill id="2950" levels="1" name="奇岩補給箱-魔法別針">
		<set name="itemConsumeCount" val="1" />
		<set name="target" val="TARGET_SELF" />
		<set name="skillType" val="EXTRACTABLE" />
		<set name="operateType" val="OP_ACTIVE" />
		<cond msgId="129">
			<and>
				<player invSize="10" />
				<player weight="80" />
			</and>
		</cond>
	</skill>
	<skill id="2951" levels="1" name="歐瑞補給箱-魔法別針">
		<set name="itemConsumeCount" val="1" />
		<set name="target" val="TARGET_SELF" />
		<set name="skillType" val="EXTRACTABLE" />
		<set name="operateType" val="OP_ACTIVE" />
		<cond msgId="129">
			<and>
				<player invSize="10" />
				<player weight="80" />
			</and>
		</cond>
	</skill>
	<skill id="2952" levels="1" name="亞丁補給箱-魔法別針">
		<set name="itemConsumeCount" val="1" />
		<set name="target" val="TARGET_SELF" />
		<set name="skillType" val="EXTRACTABLE" />
		<set name="operateType" val="OP_ACTIVE" />
		<cond msgId="129">
			<and>
				<player invSize="10" />
				<player weight="80" />
			</and>
		</cond>
	</skill>
	<skill id="2953" levels="1" name="因納得立補給箱-魔法別針">
		<set name="itemConsumeCount" val="1" />
		<set name="target" val="TARGET_SELF" />
		<set name="skillType" val="EXTRACTABLE" />
		<set name="operateType" val="OP_ACTIVE" />
		<cond msgId="129">
			<and>
				<player invSize="10" />
				<player weight="80" />
			</and>
		</cond>
	</skill>
	<skill id="2954" levels="1" name="高達特補給箱-魔法別針">
		<set name="itemConsumeCount" val="1" />
		<set name="target" val="TARGET_SELF" />
		<set name="skillType" val="EXTRACTABLE" />
		<set name="operateType" val="OP_ACTIVE" />
		<cond msgId="129">
			<and>
				<player invSize="10" />
				<player weight="80" />
			</and>
		</cond>
	</skill>
	<skill id="2955" levels="1" name="魯因補給箱-魔法別針">
		<set name="itemConsumeCount" val="1" />
		<set name="target" val="TARGET_SELF" />
		<set name="skillType" val="EXTRACTABLE" />
		<set name="operateType" val="OP_ACTIVE" />
		<cond msgId="129">
			<and>
				<player invSize="10" />
				<player weight="80" />
			</and>
		</cond>
	</skill>
	<skill id="2956" levels="1" name="修加特補給箱-魔法別針">
		<set name="itemConsumeCount" val="1" />
		<set name="target" val="TARGET_SELF" />
		<set name="skillType" val="EXTRACTABLE" />
		<set name="operateType" val="OP_ACTIVE" />
		<cond msgId="129">
			<and>
				<player invSize="10" />
				<player weight="80" />
			</and>
		</cond>
	</skill>
	<skill id="2957" levels="1" name="古魯丁補給箱-魔法小袋">
		<set name="itemConsumeCount" val="1" />
		<set name="target" val="TARGET_SELF" />
		<set name="skillType" val="EXTRACTABLE" />
		<set name="operateType" val="OP_ACTIVE" />
		<cond msgId="129">
			<and>
				<player invSize="10" />
				<player weight="80" />
			</and>
		</cond>
	</skill>
	<skill id="2958" levels="1" name="狄恩補給箱-魔法小袋">
		<set name="itemConsumeCount" val="1" />
		<set name="target" val="TARGET_SELF" />
		<set name="skillType" val="EXTRACTABLE" />
		<set name="operateType" val="OP_ACTIVE" />
		<cond msgId="129">
			<and>
				<player invSize="10" />
				<player weight="80" />
			</and>
		</cond>
	</skill>
	<skill id="2959" levels="1" name="奇岩補給箱-魔法小袋">
		<set name="itemConsumeCount" val="1" />
		<set name="target" val="TARGET_SELF" />
		<set name="skillType" val="EXTRACTABLE" />
		<set name="operateType" val="OP_ACTIVE" />
		<cond msgId="129">
			<and>
				<player invSize="10" />
				<player weight="80" />
			</and>
		</cond>
	</skill>
	<skill id="2960" levels="1" name="歐瑞補給箱-魔法小袋">
		<set name="itemConsumeCount" val="1" />
		<set name="target" val="TARGET_SELF" />
		<set name="skillType" val="EXTRACTABLE" />
		<set name="operateType" val="OP_ACTIVE" />
		<cond msgId="129">
			<and>
				<player invSize="10" />
				<player weight="80" />
			</and>
		</cond>
	</skill>
	<skill id="2961" levels="1" name="亞丁補給箱-魔法小袋">
		<set name="itemConsumeCount" val="1" />
		<set name="target" val="TARGET_SELF" />
		<set name="skillType" val="EXTRACTABLE" />
		<set name="operateType" val="OP_ACTIVE" />
		<cond msgId="129">
			<and>
				<player invSize="10" />
				<player weight="80" />
			</and>
		</cond>
	</skill>
	<skill id="2962" levels="1" name="因納得立補給箱-魔法小袋">
		<set name="itemConsumeCount" val="1" />
		<set name="target" val="TARGET_SELF" />
		<set name="skillType" val="EXTRACTABLE" />
		<set name="operateType" val="OP_ACTIVE" />
		<cond msgId="129">
			<and>
				<player invSize="10" />
				<player weight="80" />
			</and>
		</cond>
	</skill>
	<skill id="2963" levels="1" name="高達特補給箱-魔法小袋">
		<set name="itemConsumeCount" val="1" />
		<set name="target" val="TARGET_SELF" />
		<set name="skillType" val="EXTRACTABLE" />
		<set name="operateType" val="OP_ACTIVE" />
		<cond msgId="129">
			<and>
				<player invSize="10" />
				<player weight="80" />
			</and>
		</cond>
	</skill>
	<skill id="2964" levels="1" name="魯因補給箱-魔法小袋">
		<set name="itemConsumeCount" val="1" />
		<set name="target" val="TARGET_SELF" />
		<set name="skillType" val="EXTRACTABLE" />
		<set name="operateType" val="OP_ACTIVE" />
		<cond msgId="129">
			<and>
				<player invSize="10" />
				<player weight="80" />
			</and>
		</cond>
	</skill>
	<skill id="2965" levels="1" name="修加特補給箱-魔法小袋">
		<set name="itemConsumeCount" val="1" />
		<set name="target" val="TARGET_SELF" />
		<set name="skillType" val="EXTRACTABLE" />
		<set name="operateType" val="OP_ACTIVE" />
		<cond msgId="129">
			<and>
				<player invSize="10" />
				<player weight="80" />
			</and>
		</cond>
	</skill>
	<skill id="2966" levels="1" name="古魯丁補給箱-腰帶">
		<set name="itemConsumeCount" val="1" />
		<set name="target" val="TARGET_SELF" />
		<set name="skillType" val="EXTRACTABLE" />
		<set name="operateType" val="OP_ACTIVE" />
		<cond msgId="129">
			<and>
				<player invSize="10" />
				<player weight="80" />
			</and>
		</cond>
	</skill>
	<skill id="2967" levels="1" name="狄恩補給箱-腰帶">
		<set name="itemConsumeCount" val="1" />
		<set name="target" val="TARGET_SELF" />
		<set name="skillType" val="EXTRACTABLE" />
		<set name="operateType" val="OP_ACTIVE" />
		<cond msgId="129">
			<and>
				<player invSize="10" />
				<player weight="80" />
			</and>
		</cond>
	</skill>
	<skill id="2968" levels="1" name="奇岩補給箱-腰帶">
		<set name="itemConsumeCount" val="1" />
		<set name="target" val="TARGET_SELF" />
		<set name="skillType" val="EXTRACTABLE" />
		<set name="operateType" val="OP_ACTIVE" />
		<cond msgId="129">
			<and>
				<player invSize="10" />
				<player weight="80" />
			</and>
		</cond>
	</skill>
	<skill id="2969" levels="1" name="歐瑞補給箱-腰帶">
		<set name="itemConsumeCount" val="1" />
		<set name="target" val="TARGET_SELF" />
		<set name="skillType" val="EXTRACTABLE" />
		<set name="operateType" val="OP_ACTIVE" />
		<cond msgId="129">
			<and>
				<player invSize="10" />
				<player weight="80" />
			</and>
		</cond>
	</skill>
	<skill id="2970" levels="1" name="亞丁補給箱-腰帶">
		<set name="itemConsumeCount" val="1" />
		<set name="target" val="TARGET_SELF" />
		<set name="skillType" val="EXTRACTABLE" />
		<set name="operateType" val="OP_ACTIVE" />
		<cond msgId="129">
			<and>
				<player invSize="10" />
				<player weight="80" />
			</and>
		</cond>
	</skill>
	<skill id="2971" levels="1" name="因納得立補給箱-腰帶">
		<set name="itemConsumeCount" val="1" />
		<set name="target" val="TARGET_SELF" />
		<set name="skillType" val="EXTRACTABLE" />
		<set name="operateType" val="OP_ACTIVE" />
		<cond msgId="129">
			<and>
				<player invSize="10" />
				<player weight="80" />
			</and>
		</cond>
	</skill>
	<skill id="2972" levels="1" name="高達特補給箱-腰帶">
		<set name="itemConsumeCount" val="1" />
		<set name="target" val="TARGET_SELF" />
		<set name="skillType" val="EXTRACTABLE" />
		<set name="operateType" val="OP_ACTIVE" />
		<cond msgId="129">
			<and>
				<player invSize="10" />
				<player weight="80" />
			</and>
		</cond>
	</skill>
	<skill id="2973" levels="1" name="魯因補給箱-腰帶">
		<set name="itemConsumeCount" val="1" />
		<set name="target" val="TARGET_SELF" />
		<set name="skillType" val="EXTRACTABLE" />
		<set name="operateType" val="OP_ACTIVE" />
		<cond msgId="129">
			<and>
				<player invSize="10" />
				<player weight="80" />
			</and>
		</cond>
	</skill>
	<skill id="2974" levels="1" name="修加特補給箱-腰帶">
		<set name="itemConsumeCount" val="1" />
		<set name="target" val="TARGET_SELF" />
		<set name="skillType" val="EXTRACTABLE" />
		<set name="operateType" val="OP_ACTIVE" />
		<cond msgId="129">
			<and>
				<player invSize="10" />
				<player weight="80" />
			</and>
		</cond>
	</skill>
	<skill id="2975" levels="1" name="古魯丁補給箱-魔法古文夾">
		<set name="itemConsumeCount" val="1" />
		<set name="target" val="TARGET_SELF" />
		<set name="skillType" val="EXTRACTABLE" />
		<set name="operateType" val="OP_ACTIVE" />
		<cond msgId="129">
			<and>
				<player invSize="10" />
				<player weight="80" />
			</and>
		</cond>
	</skill>
	<skill id="2976" levels="1" name="狄恩補給箱-魔法古文夾">
		<set name="itemConsumeCount" val="1" />
		<set name="target" val="TARGET_SELF" />
		<set name="skillType" val="EXTRACTABLE" />
		<set name="operateType" val="OP_ACTIVE" />
		<cond msgId="129">
			<and>
				<player invSize="10" />
				<player weight="80" />
			</and>
		</cond>
	</skill>
	<skill id="2977" levels="1" name="奇岩補給箱-魔法古文夾">
		<set name="itemConsumeCount" val="1" />
		<set name="target" val="TARGET_SELF" />
		<set name="skillType" val="EXTRACTABLE" />
		<set name="operateType" val="OP_ACTIVE" />
		<cond msgId="129">
			<and>
				<player invSize="10" />
				<player weight="80" />
			</and>
		</cond>
	</skill>
	<skill id="2978" levels="1" name="歐瑞補給箱-魔法古文夾">
		<set name="itemConsumeCount" val="1" />
		<set name="target" val="TARGET_SELF" />
		<set name="skillType" val="EXTRACTABLE" />
		<set name="operateType" val="OP_ACTIVE" />
		<cond msgId="129">
			<and>
				<player invSize="10" />
				<player weight="80" />
			</and>
		</cond>
	</skill>
	<skill id="2979" levels="1" name="亞丁補給箱-魔法古文夾">
		<set name="itemConsumeCount" val="1" />
		<set name="target" val="TARGET_SELF" />
		<set name="skillType" val="EXTRACTABLE" />
		<set name="operateType" val="OP_ACTIVE" />
		<cond msgId="129">
			<and>
				<player invSize="10" />
				<player weight="80" />
			</and>
		</cond>
	</skill>
	<skill id="2980" levels="1" name="因納得立補給箱-魔法古文夾">
		<set name="itemConsumeCount" val="1" />
		<set name="target" val="TARGET_SELF" />
		<set name="skillType" val="EXTRACTABLE" />
		<set name="operateType" val="OP_ACTIVE" />
		<cond msgId="129">
			<and>
				<player invSize="10" />
				<player weight="80" />
			</and>
		</cond>
	</skill>
	<skill id="2981" levels="1" name="高達特補給箱-魔法古文夾">
		<set name="itemConsumeCount" val="1" />
		<set name="target" val="TARGET_SELF" />
		<set name="skillType" val="EXTRACTABLE" />
		<set name="operateType" val="OP_ACTIVE" />
		<cond msgId="129">
			<and>
				<player invSize="10" />
				<player weight="80" />
			</and>
		</cond>
	</skill>
	<skill id="2982" levels="1" name="魯因補給箱-魔法古文夾">
		<set name="itemConsumeCount" val="1" />
		<set name="target" val="TARGET_SELF" />
		<set name="skillType" val="EXTRACTABLE" />
		<set name="operateType" val="OP_ACTIVE" />
		<cond msgId="129">
			<and>
				<player invSize="10" />
				<player weight="80" />
			</and>
		</cond>
	</skill>
	<skill id="2983" levels="1" name="修加特補給箱-魔法古文夾">
		<set name="itemConsumeCount" val="1" />
		<set name="target" val="TARGET_SELF" />
		<set name="skillType" val="EXTRACTABLE" />
		<set name="operateType" val="OP_ACTIVE" />
		<cond msgId="129">
			<and>
				<player invSize="10" />
				<player weight="80" />
			</and>
		</cond>
	</skill>
	<skill id="2984" levels="1" name="古魯丁補給箱-魔法飾品">
		<set name="itemConsumeCount" val="1" />
		<set name="target" val="TARGET_SELF" />
		<set name="skillType" val="EXTRACTABLE" />
		<set name="operateType" val="OP_ACTIVE" />
		<cond msgId="129">
			<and>
				<player invSize="10" />
				<player weight="80" />
			</and>
		</cond>
	</skill>
	<skill id="2985" levels="1" name="狄恩補給箱-魔法飾品">
		<set name="itemConsumeCount" val="1" />
		<set name="target" val="TARGET_SELF" />
		<set name="skillType" val="EXTRACTABLE" />
		<set name="operateType" val="OP_ACTIVE" />
		<cond msgId="129">
			<and>
				<player invSize="10" />
				<player weight="80" />
			</and>
		</cond>
	</skill>
	<skill id="2986" levels="1" name="奇岩補給箱-魔法飾品">
		<set name="itemConsumeCount" val="1" />
		<set name="target" val="TARGET_SELF" />
		<set name="skillType" val="EXTRACTABLE" />
		<set name="operateType" val="OP_ACTIVE" />
		<cond msgId="129">
			<and>
				<player invSize="10" />
				<player weight="80" />
			</and>
		</cond>
	</skill>
	<skill id="2987" levels="1" name="歐瑞補給箱-魔法飾品">
		<set name="itemConsumeCount" val="1" />
		<set name="target" val="TARGET_SELF" />
		<set name="skillType" val="EXTRACTABLE" />
		<set name="operateType" val="OP_ACTIVE" />
		<cond msgId="129">
			<and>
				<player invSize="10" />
				<player weight="80" />
			</and>
		</cond>
	</skill>
	<skill id="2988" levels="1" name="亞丁補給箱-魔法飾品">
		<set name="itemConsumeCount" val="1" />
		<set name="target" val="TARGET_SELF" />
		<set name="skillType" val="EXTRACTABLE" />
		<set name="operateType" val="OP_ACTIVE" />
		<cond msgId="129">
			<and>
				<player invSize="10" />
				<player weight="80" />
			</and>
		</cond>
	</skill>
	<skill id="2989" levels="1" name="因納得立補給箱-魔法飾品">
		<set name="itemConsumeCount" val="1" />
		<set name="target" val="TARGET_SELF" />
		<set name="skillType" val="EXTRACTABLE" />
		<set name="operateType" val="OP_ACTIVE" />
		<cond msgId="129">
			<and>
				<player invSize="10" />
				<player weight="80" />
			</and>
		</cond>
	</skill>
	<skill id="2990" levels="1" name="高達特補給箱-魔法飾品">
		<set name="itemConsumeCount" val="1" />
		<set name="target" val="TARGET_SELF" />
		<set name="skillType" val="EXTRACTABLE" />
		<set name="operateType" val="OP_ACTIVE" />
		<cond msgId="129">
			<and>
				<player invSize="10" />
				<player weight="80" />
			</and>
		</cond>
	</skill>
	<skill id="2991" levels="1" name="魯因補給箱-魔法飾品">
		<set name="itemConsumeCount" val="1" />
		<set name="target" val="TARGET_SELF" />
		<set name="skillType" val="EXTRACTABLE" />
		<set name="operateType" val="OP_ACTIVE" />
		<cond msgId="129">
			<and>
				<player invSize="10" />
				<player weight="80" />
			</and>
		</cond>
	</skill>
	<skill id="2992" levels="1" name="修加特補給箱-魔法飾品">
		<set name="itemConsumeCount" val="1" />
		<set name="target" val="TARGET_SELF" />
		<set name="skillType" val="EXTRACTABLE" />
		<set name="operateType" val="OP_ACTIVE" />
		<cond msgId="129">
			<and>
				<player invSize="10" />
				<player weight="80" />
			</and>
		</cond>
	</skill>
	<skill id="2993" levels="1" name="原始藥草-欺騙者">
		<set name="target" val="TARGET_NONE" />
		<set name="skillType" val="NOTDONE" />
		<set name="reuseDelay" val="2000" />
		<set name="operateType" val="OP_PASSIVE" />
	</skill>
	<skill id="2994" levels="1" name="變身豎琴-水精靈">
		<set name="target" val="TARGET_SELF" />
		<set name="skillType" val="BUFF" />
		<set name="operateType" val="OP_ACTIVE" />
		<set name="transformId" val="125" />
		<cond msgId="1509">
			<player olympiad="false" />
		</cond>
		<for>
			<effect name="Transformation" time="3600" val="0" stackOrder="1" stackType="transform" />
		</for>
	</skill>
	<skill id="2995" levels="1" name="活動專用武器強化卷軸-D級">
		<set name="target" val="TARGET_NONE" />
		<set name="skillType" val="NOTDONE" />
		<set name="operateType" val="OP_PASSIVE" />
	</skill>
	<skill id="2996" levels="1" name="活動專用武器強化卷軸-C級">
		<set name="target" val="TARGET_NONE" />
		<set name="skillType" val="NOTDONE" />
		<set name="operateType" val="OP_PASSIVE" />
	</skill>
	<skill id="2997" levels="1" name="活動專用武器強化卷軸-B級">
		<set name="target" val="TARGET_NONE" />
		<set name="skillType" val="NOTDONE" />
		<set name="operateType" val="OP_PASSIVE" />
	</skill>
	<skill id="2998" levels="1" name="活動專用武器強化卷軸-A級">
		<set name="target" val="TARGET_NONE" />
		<set name="skillType" val="NOTDONE" />
		<set name="operateType" val="OP_PASSIVE" />
	</skill>
	<skill id="2999" levels="1" name="活動專用武器強化卷軸-S級">
		<set name="target" val="TARGET_NONE" />
		<set name="skillType" val="NOTDONE" />
		<set name="operateType" val="OP_PASSIVE" />
	</skill>
</list>